{
"meta":{"test_sets":[],"test_metrics":[],"learn_metrics":[{"best_value":"Min","name":"Logloss"}],"launch_mode":"Train","parameters":"","iteration_count":1000,"learn_sets":["learn"],"name":"experiment"},
"iterations":[
{"learn":[0.6148206075],"iteration":0,"passed_time":0.04116610051,"remaining_time":41.12493441},
{"learn":[0.5481800079],"iteration":1,"passed_time":0.07266042483,"remaining_time":36.25755199},
{"learn":[0.4905975024],"iteration":2,"passed_time":0.1385324136,"remaining_time":46.03893878},
{"learn":[0.4344415983],"iteration":3,"passed_time":0.1724771251,"remaining_time":42.94680414},
{"learn":[0.3853286107],"iteration":4,"passed_time":0.1986491392,"remaining_time":39.53117869},
{"learn":[0.3424131393],"iteration":5,"passed_time":0.2337621069,"remaining_time":38.72658904},
{"learn":[0.3023244858],"iteration":6,"passed_time":0.2626742583,"remaining_time":37.26221979},
{"learn":[0.2718266805],"iteration":7,"passed_time":0.302599069,"remaining_time":37.52228456},
{"learn":[0.246175766],"iteration":8,"passed_time":0.3396807147,"remaining_time":37.40262092},
{"learn":[0.2206615448],"iteration":9,"passed_time":0.3689431118,"remaining_time":36.52536807},
{"learn":[0.200172774],"iteration":10,"passed_time":0.4115714513,"remaining_time":37.00401503},
{"learn":[0.1814951261],"iteration":11,"passed_time":0.451578655,"remaining_time":37.17997593},
{"learn":[0.164532725],"iteration":12,"passed_time":0.4956080324,"remaining_time":37.62808677},
{"learn":[0.1503603617],"iteration":13,"passed_time":0.5410318821,"remaining_time":38.10410255},
{"learn":[0.1364631335],"iteration":14,"passed_time":0.5796043565,"remaining_time":38.06068608},
{"learn":[0.1247013728],"iteration":15,"passed_time":0.643345318,"remaining_time":39.56573706},
{"learn":[0.1137878577],"iteration":16,"passed_time":0.6831137059,"remaining_time":39.50004546},
{"learn":[0.1041071256],"iteration":17,"passed_time":0.7080088543,"remaining_time":38.62581639},
{"learn":[0.09633441766],"iteration":18,"passed_time":0.7464936977,"remaining_time":38.54264829},
{"learn":[0.08933478991],"iteration":19,"passed_time":0.7874394634,"remaining_time":38.58453371},
{"learn":[0.08155423005],"iteration":20,"passed_time":0.8187473178,"remaining_time":38.1692202},
{"learn":[0.07533359528],"iteration":21,"passed_time":0.8438519719,"remaining_time":37.51305584},
{"learn":[0.06912196477],"iteration":22,"passed_time":0.8711812171,"remaining_time":37.00626301},
{"learn":[0.06358697414],"iteration":23,"passed_time":0.896501387,"remaining_time":36.45772307},
{"learn":[0.06004633109],"iteration":24,"passed_time":0.9695519199,"remaining_time":37.81252488},
{"learn":[0.05587538878],"iteration":25,"passed_time":1.002468192,"remaining_time":37.55400075},
{"learn":[0.05239642859],"iteration":26,"passed_time":1.066293076,"remaining_time":38.42604308},
{"learn":[0.04967749119],"iteration":27,"passed_time":1.1077639,"remaining_time":38.45523252},
{"learn":[0.04685400724],"iteration":28,"passed_time":1.149704167,"remaining_time":38.49526712},
{"learn":[0.0435940663],"iteration":29,"passed_time":1.174223644,"remaining_time":37.9665645},
{"learn":[0.04098512332],"iteration":30,"passed_time":1.20535533,"remaining_time":37.67707468},
{"learn":[0.03906327089],"iteration":31,"passed_time":1.238444999,"remaining_time":37.46296121},
{"learn":[0.03683624268],"iteration":32,"passed_time":1.26582762,"remaining_time":37.09258511},
{"learn":[0.03495407104],"iteration":33,"passed_time":1.30402416,"remaining_time":37.04962759},
{"learn":[0.03323333462],"iteration":34,"passed_time":1.344299301,"remaining_time":37.06425216},
{"learn":[0.0314711233],"iteration":35,"passed_time":1.383437743,"remaining_time":37.04538846},
{"learn":[0.03007432421],"iteration":36,"passed_time":1.443330582,"remaining_time":37.56560405},
{"learn":[0.0289020141],"iteration":37,"passed_time":1.525786666,"remaining_time":38.62649402},
{"learn":[0.02776395281],"iteration":38,"passed_time":1.589596059,"remaining_time":39.16927725},
{"learn":[0.02684648236],"iteration":39,"passed_time":1.615994808,"remaining_time":38.78387539},
{"learn":[0.02581745386],"iteration":40,"passed_time":1.652877473,"remaining_time":38.66120724},
{"learn":[0.02453666131],"iteration":41,"passed_time":1.684278121,"remaining_time":38.41758191},
{"learn":[0.02367702127],"iteration":42,"passed_time":1.734401272,"remaining_time":38.60051203},
{"learn":[0.02274775306],"iteration":43,"passed_time":1.771694547,"remaining_time":38.49409062},
{"learn":[0.02160534859],"iteration":44,"passed_time":1.798328682,"remaining_time":38.16453093},
{"learn":[0.02053478956],"iteration":45,"passed_time":1.823009381,"remaining_time":37.80762934},
{"learn":[0.01978419026],"iteration":46,"passed_time":1.853931662,"remaining_time":37.59142284},
{"learn":[0.01884852648],"iteration":47,"passed_time":1.88047961,"remaining_time":37.29617892},
{"learn":[0.01807419658],"iteration":48,"passed_time":1.910484247,"remaining_time":37.07899018},
{"learn":[0.01738627156],"iteration":49,"passed_time":1.946593804,"remaining_time":36.98528227},
{"learn":[0.01676512559],"iteration":50,"passed_time":1.980858504,"remaining_time":36.85950431},
{"learn":[0.01603960196],"iteration":51,"passed_time":2.007788618,"remaining_time":36.60353096},
{"learn":[0.01534721851],"iteration":52,"passed_time":2.036417867,"remaining_time":36.38656075},
{"learn":[0.01480496426],"iteration":53,"passed_time":2.071461733,"remaining_time":36.28894072},
{"learn":[0.01420723399],"iteration":54,"passed_time":2.100206295,"remaining_time":36.0853627},
{"learn":[0.01375971238],"iteration":55,"passed_time":2.140012667,"remaining_time":36.07449925},
{"learn":[0.01341576775],"iteration":56,"passed_time":2.217569021,"remaining_time":36.68715065},
{"learn":[0.01308130622],"iteration":57,"passed_time":2.24590337,"remaining_time":36.47656853},
{"learn":[0.01274153292],"iteration":58,"passed_time":2.290830568,"remaining_time":36.53680618},
{"learn":[0.01234110395],"iteration":59,"passed_time":2.324192794,"remaining_time":36.41235377},
{"learn":[0.01198347211],"iteration":60,"passed_time":2.357152734,"remaining_time":36.28469536},
{"learn":[0.01155578891],"iteration":61,"passed_time":2.391845271,"remaining_time":36.18630426},
{"learn":[0.01132646501],"iteration":62,"passed_time":2.457908724,"remaining_time":36.55651547},
{"learn":[0.01102120181],"iteration":63,"passed_time":2.505536462,"remaining_time":36.64347076},
{"learn":[0.0107241869],"iteration":64,"passed_time":2.53635783,"remaining_time":36.48453186},
{"learn":[0.01042174796],"iteration":65,"passed_time":2.567348963,"remaining_time":36.33187775},
{"learn":[0.0100925386],"iteration":66,"passed_time":2.602434515,"remaining_time":36.23987168},
{"learn":[0.009894206127],"iteration":67,"passed_time":2.6503475,"remaining_time":36.32535104},
{"learn":[0.009582080444],"iteration":68,"passed_time":2.678135308,"remaining_time":36.13541988},
{"learn":[0.009330610434],"iteration":69,"passed_time":2.703599,"remaining_time":35.91924386},
{"learn":[0.009123509129],"iteration":70,"passed_time":2.740903458,"remaining_time":35.8633706},
{"learn":[0.008897322416],"iteration":71,"passed_time":2.771617902,"remaining_time":35.72307518},
{"learn":[0.008708876371],"iteration":72,"passed_time":2.798863443,"remaining_time":35.54173167},
{"learn":[0.008472281694],"iteration":73,"passed_time":2.828776193,"remaining_time":35.39792911},
{"learn":[0.008343545596],"iteration":74,"passed_time":2.887377436,"remaining_time":35.61098838},
{"learn":[0.008111082514],"iteration":75,"passed_time":2.917825204,"remaining_time":35.47461169},
{"learn":[0.007904944817],"iteration":76,"passed_time":2.953499552,"remaining_time":35.40363748},
{"learn":[0.007763100664],"iteration":77,"passed_time":2.982356772,"remaining_time":35.25298645},
{"learn":[0.007645052671],"iteration":78,"passed_time":3.008621122,"remaining_time":35.07519055},
{"learn":[0.007510043184],"iteration":79,"passed_time":3.033060452,"remaining_time":34.88019519},
{"learn":[0.007332665722],"iteration":80,"passed_time":3.063769863,"remaining_time":34.76054943},
{"learn":[0.007208918532],"iteration":81,"passed_time":3.100332724,"remaining_time":34.70860294},
{"learn":[0.007092998922],"iteration":82,"passed_time":3.155315284,"remaining_time":34.86053152},
{"learn":[0.006979943812],"iteration":83,"passed_time":3.183612004,"remaining_time":34.7165309},
{"learn":[0.006861155232],"iteration":84,"passed_time":3.263280313,"remaining_time":35.12825279},
{"learn":[0.006711558501],"iteration":85,"passed_time":3.292131524,"remaining_time":34.9884676},
{"learn":[0.006568107009],"iteration":86,"passed_time":3.31729684,"remaining_time":34.8125519},
{"learn":[0.006486264865],"iteration":87,"passed_time":3.383570115,"remaining_time":35.06609028},
{"learn":[0.006389645239],"iteration":88,"passed_time":3.410223289,"remaining_time":34.90689232},
{"learn":[0.006281650563],"iteration":89,"passed_time":3.445796394,"remaining_time":34.84083021},
{"learn":[0.006153337657],"iteration":90,"passed_time":3.471595929,"remaining_time":34.67780988},
{"learn":[0.006008567413],"iteration":91,"passed_time":3.498255559,"remaining_time":34.52626139},
{"learn":[0.005918813248],"iteration":92,"passed_time":3.548797376,"remaining_time":34.6103142},
{"learn":[0.005802198251],"iteration":93,"passed_time":3.578518629,"remaining_time":34.49082849},
{"learn":[0.005707686146],"iteration":94,"passed_time":3.615125237,"remaining_time":34.43882463},
{"learn":[0.005638222893],"iteration":95,"passed_time":3.676337281,"remaining_time":34.61884273},
{"learn":[0.00554142942],"iteration":96,"passed_time":3.708529049,"remaining_time":34.52372919},
{"learn":[0.005429222186],"iteration":97,"passed_time":3.736990603,"remaining_time":34.39556657},
{"learn":[0.005362238487],"iteration":98,"passed_time":3.784649849,"remaining_time":34.44413651},
{"learn":[0.005290384591],"iteration":99,"passed_time":3.845612136,"remaining_time":34.61050923},
{"learn":[0.005224793653],"iteration":100,"passed_time":3.872186593,"remaining_time":34.46629453},
{"learn":[0.005177240074],"iteration":101,"passed_time":3.93344539,"remaining_time":34.62974471},
{"learn":[0.00509677281],"iteration":102,"passed_time":3.970751631,"remaining_time":34.58023508},
{"learn":[0.005025870601],"iteration":103,"passed_time":3.998861285,"remaining_time":34.45172799},
{"learn":[0.004985427856],"iteration":104,"passed_time":4.061490047,"remaining_time":34.61936754},
{"learn":[0.004921825727],"iteration":105,"passed_time":4.09216149,"remaining_time":34.51313559},
{"learn":[0.004859697819],"iteration":106,"passed_time":4.142419326,"remaining_time":34.57177998},
{"learn":[0.004817322393],"iteration":107,"passed_time":4.204411106,"remaining_time":34.72532135},
{"learn":[0.004716102282],"iteration":108,"passed_time":4.227647368,"remaining_time":34.5581083},
{"learn":[0.004635607203],"iteration":109,"passed_time":4.252106366,"remaining_time":34.40340605},
{"learn":[0.004574109117],"iteration":110,"passed_time":4.300368021,"remaining_time":34.44168622},
{"learn":[0.004507619143],"iteration":111,"passed_time":4.333737188,"remaining_time":34.36034485},
{"learn":[0.004461116592],"iteration":112,"passed_time":4.396525693,"remaining_time":34.51078132},
{"learn":[0.004395941893],"iteration":113,"passed_time":4.4272922,"remaining_time":34.40860429},
{"learn":[0.004334194958],"iteration":114,"passed_time":4.457592759,"remaining_time":34.3040834},
{"learn":[0.004294038812],"iteration":115,"passed_time":4.494089979,"remaining_time":34.24806501},
{"learn":[0.004255046447],"iteration":116,"passed_time":4.539403349,"remaining_time":34.25891588},
{"learn":[0.004210763176],"iteration":117,"passed_time":4.563624231,"remaining_time":34.11115739},
{"learn":[0.004167434573],"iteration":118,"passed_time":4.601318582,"remaining_time":34.06522412},
{"learn":[0.004124748707],"iteration":119,"passed_time":4.638051507,"remaining_time":34.01237771},
{"learn":[0.004087607314],"iteration":120,"passed_time":4.698694733,"remaining_time":34.13349314},
{"learn":[0.004053706427],"iteration":121,"passed_time":4.762578765,"remaining_time":34.27495209},
{"learn":[0.004018744081],"iteration":122,"passed_time":4.798573301,"remaining_time":34.21421777},
{"learn":[0.003974880278],"iteration":123,"passed_time":4.848036255,"remaining_time":34.24903032},
{"learn":[0.003914838284],"iteration":124,"passed_time":4.875001207,"remaining_time":34.12500845},
{"learn":[0.003858835747],"iteration":125,"passed_time":4.907334202,"remaining_time":34.03976264},
{"learn":[0.003823930025],"iteration":126,"passed_time":4.956129202,"remaining_time":34.06851018},
{"learn":[0.003756337613],"iteration":127,"passed_time":4.979561847,"remaining_time":33.92326508},
{"learn":[0.00370238622],"iteration":128,"passed_time":5.006352784,"remaining_time":33.80258353},
{"learn":[0.003677735229],"iteration":129,"passed_time":5.067836677,"remaining_time":33.91552237},
{"learn":[0.003633226454],"iteration":130,"passed_time":5.106216179,"remaining_time":33.87253328},
{"learn":[0.003594873846],"iteration":131,"passed_time":5.143293039,"remaining_time":33.82104817},
{"learn":[0.003557277719],"iteration":132,"passed_time":5.180337147,"remaining_time":33.76956622},
{"learn":[0.003529802461],"iteration":133,"passed_time":5.206378558,"remaining_time":33.64719277},
{"learn":[0.003493639578],"iteration":134,"passed_time":5.243022471,"remaining_time":33.59418102},
{"learn":[0.003445895513],"iteration":135,"passed_time":5.273748222,"remaining_time":33.50381223},
{"learn":[0.003402947138],"iteration":136,"passed_time":5.30402045,"remaining_time":33.41145729},
{"learn":[0.003369212896],"iteration":137,"passed_time":5.341633048,"remaining_time":33.36585281},
{"learn":[0.003323006382],"iteration":138,"passed_time":5.372244932,"remaining_time":33.27699918},
{"learn":[0.003281341493],"iteration":139,"passed_time":5.403140286,"remaining_time":33.1907189},
{"learn":[0.003245311975],"iteration":140,"passed_time":5.433964274,"remaining_time":33.10478944},
{"learn":[0.003205139438],"iteration":141,"passed_time":5.495933973,"remaining_time":33.2078264},
{"learn":[0.003172739347],"iteration":142,"passed_time":5.522484086,"remaining_time":33.09628575},
{"learn":[0.003141538302],"iteration":143,"passed_time":5.559798796,"remaining_time":33.04991507},
{"learn":[0.003118829926],"iteration":144,"passed_time":5.581109288,"remaining_time":32.9092996},
{"learn":[0.00309027185],"iteration":145,"passed_time":5.620453851,"remaining_time":32.8758054},
{"learn":[0.003054261208],"iteration":146,"passed_time":5.649808665,"remaining_time":32.78426388},
{"learn":[0.003036062419],"iteration":147,"passed_time":5.713313645,"remaining_time":32.89015693},
{"learn":[0.003012639284],"iteration":148,"passed_time":5.76200828,"remaining_time":32.90918823},
{"learn":[0.002988605698],"iteration":149,"passed_time":5.788784939,"remaining_time":32.80311466},
{"learn":[0.002952101827],"iteration":150,"passed_time":5.81893591,"remaining_time":32.7170635},
{"learn":[0.002924458186],"iteration":151,"passed_time":5.856367976,"remaining_time":32.67236871},
{"learn":[0.002902168532],"iteration":152,"passed_time":5.882946664,"remaining_time":32.56768513},
{"learn":[0.002879494925],"iteration":153,"passed_time":5.944913733,"remaining_time":32.6584222},
{"learn":[0.00284512341],"iteration":154,"passed_time":5.974103532,"remaining_time":32.5684999},
{"learn":[0.002823253224],"iteration":155,"passed_time":6.023617205,"remaining_time":32.5893136},
{"learn":[0.002804132303],"iteration":156,"passed_time":6.086305248,"remaining_time":32.67997022},
{"learn":[0.002784606814],"iteration":157,"passed_time":6.146745563,"remaining_time":32.75670737},
{"learn":[0.002764199674],"iteration":158,"passed_time":6.211183262,"remaining_time":32.85286241},
{"learn":[0.002744553735],"iteration":159,"passed_time":6.238119036,"remaining_time":32.75012494},
{"learn":[0.002722109109],"iteration":160,"passed_time":6.275222581,"remaining_time":32.70131519},
{"learn":[0.002697542061],"iteration":161,"passed_time":6.300772498,"remaining_time":32.5928849},
{"learn":[0.002673789362],"iteration":162,"passed_time":6.32745417,"remaining_time":32.49128307},
{"learn":[0.002650524427],"iteration":163,"passed_time":6.35414101,"remaining_time":32.39062125},
{"learn":[0.00262818411],"iteration":164,"passed_time":6.381282199,"remaining_time":32.29315537},
{"learn":[0.00259942313],"iteration":165,"passed_time":6.408753658,"remaining_time":32.19819609},
{"learn":[0.00257409364],"iteration":166,"passed_time":6.437836657,"remaining_time":32.11208345},
{"learn":[0.002546796699],"iteration":167,"passed_time":6.470830612,"remaining_time":32.04601827},
{"learn":[0.002519380301],"iteration":168,"passed_time":6.508916686,"remaining_time":32.00538323},
{"learn":[0.002499112984],"iteration":169,"passed_time":6.539622021,"remaining_time":31.92874281},
{"learn":[0.002485541006],"iteration":170,"passed_time":6.610309419,"remaining_time":32.04647081},
{"learn":[0.002470835795],"iteration":171,"passed_time":6.691478457,"remaining_time":32.21246606},
{"learn":[0.002445001403],"iteration":172,"passed_time":6.737210525,"remaining_time":32.20620291},
{"learn":[0.002431161453],"iteration":173,"passed_time":6.775955195,"remaining_time":32.16631604},
{"learn":[0.002415431788],"iteration":174,"passed_time":6.804102311,"remaining_time":32.07648232},
{"learn":[0.00239756306],"iteration":175,"passed_time":6.852807969,"remaining_time":32.08360094},
{"learn":[0.002379132311],"iteration":176,"passed_time":6.87924319,"remaining_time":31.98653755},
{"learn":[0.002357252936],"iteration":177,"passed_time":6.913254853,"remaining_time":31.92525556},
{"learn":[0.002337833246],"iteration":178,"passed_time":6.946899581,"remaining_time":31.86259529},
{"learn":[0.002327153583],"iteration":179,"passed_time":7.008110433,"remaining_time":31.92583642},
{"learn":[0.002313579122],"iteration":180,"passed_time":7.070319404,"remaining_time":31.99221874},
{"learn":[0.002294805149],"iteration":181,"passed_time":7.108768082,"remaining_time":31.95039721},
{"learn":[0.002277886371],"iteration":182,"passed_time":7.135530806,"remaining_time":31.85644081},
{"learn":[0.002259584765],"iteration":183,"passed_time":7.167389252,"remaining_time":31.7858132},
{"learn":[0.002241611729],"iteration":184,"passed_time":7.201508898,"remaining_time":31.72556623},
{"learn":[0.002228329082],"iteration":185,"passed_time":7.227504871,"remaining_time":31.6300482},
{"learn":[0.002214625974],"iteration":186,"passed_time":7.290107776,"remaining_time":31.69442578},
{"learn":[0.002198906243],"iteration":187,"passed_time":7.317923054,"remaining_time":31.60719957},
{"learn":[0.002178088824],"iteration":188,"passed_time":7.350109253,"remaining_time":31.53935769},
{"learn":[0.002164076269],"iteration":189,"passed_time":7.421434153,"remaining_time":31.6387456},
{"learn":[0.002145925661],"iteration":190,"passed_time":7.454327105,"remaining_time":31.5735635},
{"learn":[0.002133691063],"iteration":191,"passed_time":7.481009078,"remaining_time":31.48257987},
{"learn":[0.002121821543],"iteration":192,"passed_time":7.517702097,"remaining_time":31.43412224},
{"learn":[0.002107379089],"iteration":193,"passed_time":7.545271618,"remaining_time":31.34788105},
{"learn":[0.002090185384],"iteration":194,"passed_time":7.573132765,"remaining_time":31.26344552},
{"learn":[0.002078793819],"iteration":195,"passed_time":7.599481534,"remaining_time":31.17338344},
{"learn":[0.002063375711],"iteration":196,"passed_time":7.629970683,"remaining_time":31.10084497},
{"learn":[0.002049247051],"iteration":197,"passed_time":7.667259763,"remaining_time":31.05627439},
{"learn":[0.002036053315],"iteration":198,"passed_time":7.731318179,"remaining_time":31.11952694},
{"learn":[0.00201790457],"iteration":199,"passed_time":7.76227536,"remaining_time":31.04910144},
{"learn":[0.00200337631],"iteration":200,"passed_time":7.792862637,"remaining_time":30.97759824},
{"learn":[0.001994788771],"iteration":201,"passed_time":7.85524813,"remaining_time":31.03211885},
{"learn":[0.001984374846],"iteration":202,"passed_time":7.88352453,"remaining_time":30.95157168},
{"learn":[0.001975911483],"iteration":203,"passed_time":7.947292668,"remaining_time":31.01002433},
{"learn":[0.001959018161],"iteration":204,"passed_time":7.970957207,"remaining_time":30.91176088},
{"learn":[0.001949082067],"iteration":205,"passed_time":8.011394479,"remaining_time":30.87886998},
{"learn":[0.001940849548],"iteration":206,"passed_time":8.078480191,"remaining_time":30.94799416},
{"learn":[0.001928955813],"iteration":207,"passed_time":8.116384572,"remaining_time":30.9046951},
{"learn":[0.001916788022],"iteration":208,"passed_time":8.143215953,"remaining_time":30.8195398},
{"learn":[0.001908680052],"iteration":209,"passed_time":8.204243093,"remaining_time":30.86358116},
{"learn":[0.001892545074],"iteration":210,"passed_time":8.243316911,"remaining_time":30.82453575},
{"learn":[0.00188094005],"iteration":211,"passed_time":8.267921053,"remaining_time":30.73170655},
{"learn":[0.001871642719],"iteration":212,"passed_time":8.294574907,"remaining_time":30.64709132},
{"learn":[0.001859097183],"iteration":213,"passed_time":8.326388711,"remaining_time":30.58196975},
{"learn":[0.001845503102],"iteration":214,"passed_time":8.35763835,"remaining_time":30.51509816},
{"learn":[0.001836747552],"iteration":215,"passed_time":8.382626121,"remaining_time":30.42582814},
{"learn":[0.001828083768],"iteration":216,"passed_time":8.408801064,"remaining_time":30.34143425},
{"learn":[0.001817098384],"iteration":217,"passed_time":8.433771525,"remaining_time":30.25325382},
{"learn":[0.001810635378],"iteration":218,"passed_time":8.499653684,"remaining_time":30.31155035},
{"learn":[0.001797806099],"iteration":219,"passed_time":8.531044577,"remaining_time":30.24643077},
{"learn":[0.001786894475],"iteration":220,"passed_time":8.567924647,"remaining_time":30.20096516},
{"learn":[0.001776448141],"iteration":221,"passed_time":8.59403886,"remaining_time":30.1178479},
{"learn":[0.001762654757],"iteration":222,"passed_time":8.617408416,"remaining_time":30.02567865},
{"learn":[0.001752503837],"iteration":223,"passed_time":8.644153265,"remaining_time":29.94581667},
{"learn":[0.001744663467],"iteration":224,"passed_time":8.668356445,"remaining_time":29.8576722},
{"learn":[0.001734899233],"iteration":225,"passed_time":8.695710038,"remaining_time":29.78088305},
{"learn":[0.001721310616],"iteration":226,"passed_time":8.72979622,"remaining_time":29.72745585},
{"learn":[0.001713744675],"iteration":227,"passed_time":8.761621228,"remaining_time":29.66654205},
{"learn":[0.001707954705],"iteration":228,"passed_time":8.816780829,"remaining_time":29.6844455},
{"learn":[0.00170050847],"iteration":229,"passed_time":8.898274759,"remaining_time":29.78987637},
{"learn":[0.001691257829],"iteration":230,"passed_time":8.939408158,"remaining_time":29.75932846},
{"learn":[0.001685585454],"iteration":231,"passed_time":9.00168104,"remaining_time":29.79866827},
{"learn":[0.001679610709],"iteration":232,"passed_time":9.064774325,"remaining_time":29.83983651},
{"learn":[0.001672413448],"iteration":233,"passed_time":9.091762999,"remaining_time":29.76192503},
{"learn":[0.001663340876],"iteration":234,"passed_time":9.115816247,"remaining_time":29.67489119},
{"learn":[0.001652465512],"iteration":235,"passed_time":9.147386493,"remaining_time":29.61272577},
{"learn":[0.001643731197],"iteration":236,"passed_time":9.186990678,"remaining_time":29.57668307},
{"learn":[0.001636312157],"iteration":237,"passed_time":9.250140592,"remaining_time":29.61599635},
{"learn":[0.00162783439],"iteration":238,"passed_time":9.276709225,"remaining_time":29.53797373},
{"learn":[0.001622395466],"iteration":239,"passed_time":9.339729548,"remaining_time":29.57581023},
{"learn":[0.00161581412],"iteration":240,"passed_time":9.364988346,"remaining_time":29.49388446},
{"learn":[0.001607449104],"iteration":241,"passed_time":9.391200793,"remaining_time":29.41541405},
{"learn":[0.001602614919],"iteration":242,"passed_time":9.455649834,"remaining_time":29.4564894},
{"learn":[0.00159589226],"iteration":243,"passed_time":9.515936029,"remaining_time":29.48380179},
{"learn":[0.00158950078],"iteration":244,"passed_time":9.577865787,"remaining_time":29.51546395},
{"learn":[0.001583096758],"iteration":245,"passed_time":9.60559726,"remaining_time":29.44154607},
{"learn":[0.001576920723],"iteration":246,"passed_time":9.630881805,"remaining_time":29.36054251},
{"learn":[0.001571454604],"iteration":247,"passed_time":9.696028069,"remaining_time":29.40085931},
{"learn":[0.00156496577],"iteration":248,"passed_time":9.745846947,"remaining_time":29.39410063},
{"learn":[0.001554020246],"iteration":249,"passed_time":9.771841324,"remaining_time":29.31552397},
{"learn":[0.001548198859],"iteration":250,"passed_time":9.797192574,"remaining_time":29.23544716},
{"learn":[0.001538767293],"iteration":251,"passed_time":9.827870454,"remaining_time":29.17161548},
{"learn":[0.0015336742],"iteration":252,"passed_time":9.891775934,"remaining_time":29.20615266},
{"learn":[0.001527274276],"iteration":253,"passed_time":9.955874905,"remaining_time":29.24048299},
{"learn":[0.001521642506],"iteration":254,"passed_time":9.98020427,"remaining_time":29.15785169},
{"learn":[0.001514039685],"iteration":255,"passed_time":10.00577611,"remaining_time":29.07928681},
{"learn":[0.001503360271],"iteration":256,"passed_time":10.03612779,"remaining_time":29.0149531},
{"learn":[0.001497787113],"iteration":257,"passed_time":10.06221702,"remaining_time":28.93862415},
{"learn":[0.001491832485],"iteration":258,"passed_time":10.12523911,"remaining_time":28.96834819},
{"learn":[0.00148448348],"iteration":259,"passed_time":10.15028708,"remaining_time":28.8892786},
{"learn":[0.001477399468],"iteration":260,"passed_time":10.17660496,"remaining_time":28.81421865},
{"learn":[0.00146763362],"iteration":261,"passed_time":10.20812215,"remaining_time":28.75417613},
{"learn":[0.001462979366],"iteration":262,"passed_time":10.27178313,"remaining_time":28.78442648},
{"learn":[0.001458650952],"iteration":263,"passed_time":10.33623552,"remaining_time":28.81617174},
{"learn":[0.001448805382],"iteration":264,"passed_time":10.36383071,"remaining_time":28.74496443},
{"learn":[0.001443774377],"iteration":265,"passed_time":10.42729251,"remaining_time":28.77305526},
{"learn":[0.001438689232],"iteration":266,"passed_time":10.45582391,"remaining_time":28.70456527},
{"learn":[0.001431939627],"iteration":267,"passed_time":10.48042169,"remaining_time":28.6256294},
{"learn":[0.001426383356],"iteration":268,"passed_time":10.54382938,"remaining_time":28.65256236},
{"learn":[0.001419822499],"iteration":269,"passed_time":10.5705777,"remaining_time":28.57971009},
{"learn":[0.001411835353],"iteration":270,"passed_time":10.60127423,"remaining_time":28.51781886},
{"learn":[0.001402810216],"iteration":271,"passed_time":10.62936393,"remaining_time":28.44917993},
{"learn":[0.001398689921],"iteration":272,"passed_time":10.69379874,"remaining_time":28.47762522},
{"learn":[0.001393337175],"iteration":273,"passed_time":10.75700267,"remaining_time":28.50213116},
{"learn":[0.001389073332],"iteration":274,"passed_time":10.8209693,"remaining_time":28.52800996},
{"learn":[0.001384983212],"iteration":275,"passed_time":10.88725487,"remaining_time":28.55932074},
{"learn":[0.001380294313],"iteration":276,"passed_time":10.91161126,"remaining_time":28.48048715},
{"learn":[0.001376949996],"iteration":277,"passed_time":10.9765825,"remaining_time":28.50752722},
{"learn":[0.001372988274],"iteration":278,"passed_time":11.04190076,"remaining_time":28.53480447},
{"learn":[0.0013689251],"iteration":279,"passed_time":11.10670379,"remaining_time":28.56009546},
{"learn":[0.001364167283],"iteration":280,"passed_time":11.15660848,"remaining_time":28.54662454},
{"learn":[0.00136038214],"iteration":281,"passed_time":11.21905213,"remaining_time":28.56482067},
{"learn":[0.001354014128],"iteration":282,"passed_time":11.25661239,"remaining_time":28.51940311},
{"learn":[0.001349654545],"iteration":283,"passed_time":11.28387105,"remaining_time":28.44806926},
{"learn":[0.001344680786],"iteration":284,"passed_time":11.34879599,"remaining_time":28.47154081},
{"learn":[0.00134109656],"iteration":285,"passed_time":11.39438905,"remaining_time":28.4461321},
{"learn":[0.00133678938],"iteration":286,"passed_time":11.42093104,"remaining_time":28.37325377},
{"learn":[0.001328237355],"iteration":287,"passed_time":11.44579701,"remaining_time":28.29655373},
{"learn":[0.001322533687],"iteration":288,"passed_time":11.47282246,"remaining_time":28.22552515},
{"learn":[0.001316582163],"iteration":289,"passed_time":11.51056029,"remaining_time":28.18102693},
{"learn":[0.001310990254],"iteration":290,"passed_time":11.53694541,"remaining_time":28.1089151},
{"learn":[0.001306267331],"iteration":291,"passed_time":11.60120467,"remaining_time":28.1289483},
{"learn":[0.00130282864],"iteration":292,"passed_time":11.66198816,"remaining_time":28.14001921},
{"learn":[0.001299237957],"iteration":293,"passed_time":11.72699785,"remaining_time":28.16074994},
{"learn":[0.001295525953],"iteration":294,"passed_time":11.79128675,"remaining_time":28.17917681},
{"learn":[0.001287519311],"iteration":295,"passed_time":11.82362648,"remaining_time":28.12105757},
{"learn":[0.001281009118],"iteration":296,"passed_time":11.8542118,"remaining_time":28.05895925},
{"learn":[0.001275634766],"iteration":297,"passed_time":11.8806995,"remaining_time":27.98741963},
{"learn":[0.001271140824],"iteration":298,"passed_time":11.94233424,"remaining_time":27.99858295},
{"learn":[0.00126605009],"iteration":299,"passed_time":11.96849051,"remaining_time":27.92647785},
{"learn":[0.001258742561],"iteration":300,"passed_time":11.99865357,"remaining_time":27.86398288},
{"learn":[0.001253688087],"iteration":301,"passed_time":12.0238174,"remaining_time":27.7901475},
{"learn":[0.001250988742],"iteration":302,"passed_time":12.08718287,"remaining_time":27.80450976},
{"learn":[0.00124675855],"iteration":303,"passed_time":12.1379534,"remaining_time":27.78952489},
{"learn":[0.001242429018],"iteration":304,"passed_time":12.17612839,"remaining_time":27.74560405},
{"learn":[0.001237642765],"iteration":305,"passed_time":12.20300662,"remaining_time":27.67609997},
{"learn":[0.00123438562],"iteration":306,"passed_time":12.26744438,"remaining_time":27.69165784},
{"learn":[0.001231119906],"iteration":307,"passed_time":12.33254741,"remaining_time":27.70819094},
{"learn":[0.001225925982],"iteration":308,"passed_time":12.3710812,"remaining_time":27.66478029},
{"learn":[0.001223354538],"iteration":309,"passed_time":12.43492186,"remaining_time":27.6777293},
{"learn":[0.001219241321],"iteration":310,"passed_time":12.49914447,"remaining_time":27.69103067},
{"learn":[0.001214688023],"iteration":311,"passed_time":12.52348186,"remaining_time":27.61588307},
{"learn":[0.001210052893],"iteration":312,"passed_time":12.55102842,"remaining_time":27.54810392},
{"learn":[0.001203489676],"iteration":313,"passed_time":12.58084583,"remaining_time":27.48554217},
{"learn":[0.001198937247],"iteration":314,"passed_time":12.60630499,"remaining_time":27.41371086},
{"learn":[0.001196557035],"iteration":315,"passed_time":12.67079632,"remaining_time":27.42666038},
{"learn":[0.001193600148],"iteration":316,"passed_time":12.74593398,"remaining_time":27.46205966},
{"learn":[0.001191169024],"iteration":317,"passed_time":12.80524214,"remaining_time":27.4628149},
{"learn":[0.001185512791],"iteration":318,"passed_time":12.83463819,"remaining_time":27.39933732},
{"learn":[0.001182016109],"iteration":319,"passed_time":12.86291231,"remaining_time":27.33368865},
{"learn":[0.001179033021],"iteration":320,"passed_time":12.95114009,"remaining_time":27.39509072},
{"learn":[0.001176185782],"iteration":321,"passed_time":13.0150025,"remaining_time":27.40425991},
{"learn":[0.001170713082],"iteration":322,"passed_time":13.04997788,"remaining_time":27.35243042},
{"learn":[0.00116726011],"iteration":323,"passed_time":13.0789616,"remaining_time":27.28820384},
{"learn":[0.001164599011],"iteration":324,"passed_time":13.12902531,"remaining_time":27.26797565},
{"learn":[0.001162368308],"iteration":325,"passed_time":13.19380826,"remaining_time":27.27799622},
{"learn":[0.001155778269],"iteration":326,"passed_time":13.21877548,"remaining_time":27.20561437},
{"learn":[0.001151691626],"iteration":327,"passed_time":13.24683567,"remaining_time":27.13985844},
{"learn":[0.00114841784],"iteration":328,"passed_time":13.27208874,"remaining_time":27.06860651},
{"learn":[0.001144463569],"iteration":329,"passed_time":13.32589048,"remaining_time":27.05559583},
{"learn":[0.001141230762],"iteration":330,"passed_time":13.35238043,"remaining_time":26.98713748},
{"learn":[0.001138546815],"iteration":331,"passed_time":13.41534824,"remaining_time":26.99232718},
{"learn":[0.001132307698],"iteration":332,"passed_time":13.44618707,"remaining_time":26.93275309},
{"learn":[0.001129230733],"iteration":333,"passed_time":13.47217917,"remaining_time":26.8636866},
{"learn":[0.001126510898],"iteration":334,"passed_time":13.53823765,"remaining_time":26.87441206},
{"learn":[0.001120417565],"iteration":335,"passed_time":13.56535524,"remaining_time":26.80772583},
{"learn":[0.001117318496],"iteration":336,"passed_time":13.59280509,"remaining_time":26.74192811},
{"learn":[0.001114346584],"iteration":337,"passed_time":13.65365159,"remaining_time":26.74176731},
{"learn":[0.001111824314],"iteration":338,"passed_time":13.68584894,"remaining_time":26.68538687},
{"learn":[0.001105933761],"iteration":339,"passed_time":13.71668655,"remaining_time":26.62650919},
{"learn":[0.001103217155],"iteration":340,"passed_time":13.77928592,"remaining_time":26.62917719},
{"learn":[0.001100344459],"iteration":341,"passed_time":13.80427758,"remaining_time":26.55910716},
{"learn":[0.001096603895],"iteration":342,"passed_time":13.83103742,"remaining_time":26.49268684},
{"learn":[0.001093652099],"iteration":343,"passed_time":13.8599725,"remaining_time":26.43064523},
{"learn":[0.001091284553],"iteration":344,"passed_time":13.92011152,"remaining_time":26.42803781},
{"learn":[0.001089249675],"iteration":345,"passed_time":13.9823307,"remaining_time":26.42902971},
{"learn":[0.00108353508],"iteration":346,"passed_time":14.0100516,"remaining_time":26.36473687},
{"learn":[0.001080699638],"iteration":347,"passed_time":14.03479496,"remaining_time":26.29507562},
{"learn":[0.001077984398],"iteration":348,"passed_time":14.06187114,"remaining_time":26.23002324},
{"learn":[0.001075792437],"iteration":349,"passed_time":14.1241505,"remaining_time":26.23056522},
{"learn":[0.001072931414],"iteration":350,"passed_time":14.14969181,"remaining_time":26.16282046},
{"learn":[0.001070534438],"iteration":351,"passed_time":14.21157535,"remaining_time":26.16221826},
{"learn":[0.001068289826],"iteration":352,"passed_time":14.27183163,"remaining_time":26.1582863},
{"learn":[0.001065783203],"iteration":353,"passed_time":14.33128713,"remaining_time":26.15257482},
{"learn":[0.001063422238],"iteration":354,"passed_time":14.3914359,"remaining_time":26.14782015},
{"learn":[0.001058803499],"iteration":355,"passed_time":14.41898757,"remaining_time":26.0837865},
{"learn":[0.001056326429],"iteration":356,"passed_time":14.47870912,"remaining_time":26.07789906},
{"learn":[0.001053350419],"iteration":357,"passed_time":14.52550933,"remaining_time":26.04853907},
{"learn":[0.001050808902],"iteration":358,"passed_time":14.55003383,"remaining_time":25.97930831},
{"learn":[0.00104836536],"iteration":359,"passed_time":14.57550721,"remaining_time":25.91201282},
{"learn":[0.001045216868],"iteration":360,"passed_time":14.61817289,"remaining_time":25.87538083},
{"learn":[0.001041775197],"iteration":361,"passed_time":14.6433982,"remaining_time":25.80797804},
{"learn":[0.001039346804],"iteration":362,"passed_time":14.70284916,"remaining_time":25.80086753},
{"learn":[0.001037182659],"iteration":363,"passed_time":14.74698526,"remaining_time":25.76671051},
{"learn":[0.001032072678],"iteration":364,"passed_time":14.77664785,"remaining_time":25.70731887},
{"learn":[0.001029878358],"iteration":365,"passed_time":14.83678717,"remaining_time":25.70088269},
{"learn":[0.001027358137],"iteration":366,"passed_time":14.86095619,"remaining_time":25.63211244},
{"learn":[0.001022537922],"iteration":367,"passed_time":14.89062411,"remaining_time":25.57302836},
{"learn":[0.001018788169],"iteration":368,"passed_time":14.92609057,"remaining_time":25.52401938},
{"learn":[0.001016578761],"iteration":369,"passed_time":14.95037899,"remaining_time":25.45605072},
{"learn":[0.001013297836],"iteration":370,"passed_time":14.97528106,"remaining_time":25.38935792},
{"learn":[0.001010443767],"iteration":371,"passed_time":15.02175949,"remaining_time":25.35931441},
{"learn":[0.001007006566],"iteration":372,"passed_time":15.04936791,"remaining_time":25.29746294},
{"learn":[0.001004867566],"iteration":373,"passed_time":15.11555604,"remaining_time":25.3003692},
{"learn":[0.001002835234],"iteration":374,"passed_time":15.21305665,"remaining_time":25.35509441},
{"learn":[0.001000641721],"iteration":375,"passed_time":15.28599702,"remaining_time":25.36825038},
{"learn":[0.0009984722361],"iteration":376,"passed_time":15.3456833,"remaining_time":25.35904694},
{"learn":[0.0009938793878],"iteration":377,"passed_time":15.36957993,"remaining_time":25.29068444},
{"learn":[0.0009888725355],"iteration":378,"passed_time":15.39791217,"remaining_time":25.22982443},
{"learn":[0.0009868240605],"iteration":379,"passed_time":15.46164129,"remaining_time":25.22688841},
{"learn":[0.0009845629334],"iteration":380,"passed_time":15.48835967,"remaining_time":25.16350298},
{"learn":[0.0009818992267],"iteration":381,"passed_time":15.55417274,"remaining_time":25.16355695},
{"learn":[0.0009799050788],"iteration":382,"passed_time":15.61476041,"remaining_time":25.15484901},
{"learn":[0.0009768749277],"iteration":383,"passed_time":15.64040441,"remaining_time":25.08981542},
{"learn":[0.0009748519709],"iteration":384,"passed_time":15.70054549,"remaining_time":25.08009215},
{"learn":[0.0009731200834],"iteration":385,"passed_time":15.75960012,"remaining_time":25.06837946},
{"learn":[0.0009710205098],"iteration":386,"passed_time":15.78487719,"remaining_time":25.00291917},
{"learn":[0.000968075792],"iteration":387,"passed_time":15.81031335,"remaining_time":24.93791693},
{"learn":[0.0009633512547],"iteration":388,"passed_time":15.83945298,"remaining_time":24.87893514},
{"learn":[0.0009614436577],"iteration":389,"passed_time":15.90427058,"remaining_time":24.8759104},
{"learn":[0.0009593978524],"iteration":390,"passed_time":15.96505434,"remaining_time":24.86628668},
{"learn":[0.0009574564795],"iteration":391,"passed_time":16.02562352,"remaining_time":24.85606913},
{"learn":[0.0009554193666],"iteration":392,"passed_time":16.08616673,"remaining_time":24.84555523},
{"learn":[0.0009526055306],"iteration":393,"passed_time":16.11059847,"remaining_time":24.77924537},
{"learn":[0.0009506066019],"iteration":394,"passed_time":16.17391085,"remaining_time":24.7726989},
{"learn":[0.0009461001803],"iteration":395,"passed_time":16.20523363,"remaining_time":24.71707352},
{"learn":[0.0009445725009],"iteration":396,"passed_time":16.27192457,"remaining_time":24.71529096},
{"learn":[0.0009423942616],"iteration":397,"passed_time":16.33544344,"remaining_time":24.70838429},
{"learn":[0.0009386599064],"iteration":398,"passed_time":16.36323526,"remaining_time":24.64737943},
{"learn":[0.0009372210751],"iteration":399,"passed_time":16.42124162,"remaining_time":24.63186244},
{"learn":[0.0009340287497],"iteration":400,"passed_time":16.48422202,"remaining_time":24.62356356},
{"learn":[0.0009297508126],"iteration":401,"passed_time":16.51255685,"remaining_time":24.56345522},
{"learn":[0.0009280120333],"iteration":402,"passed_time":16.58798308,"remaining_time":24.57326525},
{"learn":[0.0009237478177],"iteration":403,"passed_time":16.61344011,"remaining_time":24.5089364},
{"learn":[0.000921548903],"iteration":404,"passed_time":16.65474384,"remaining_time":24.46808046},
{"learn":[0.0009196055432],"iteration":405,"passed_time":16.67919621,"remaining_time":24.40256786},
{"learn":[0.0009169875334],"iteration":406,"passed_time":16.73984135,"remaining_time":24.38998998},
{"learn":[0.0009153377886],"iteration":407,"passed_time":16.78429514,"remaining_time":24.35368315},
{"learn":[0.0009127491464],"iteration":408,"passed_time":16.81039652,"remaining_time":24.29081746},
{"learn":[0.0009095123038],"iteration":409,"passed_time":16.84085677,"remaining_time":24.23440365},
{"learn":[0.0009076627592],"iteration":410,"passed_time":16.90465741,"remaining_time":24.2258959},
{"learn":[0.0009043115502],"iteration":411,"passed_time":16.93529833,"remaining_time":24.16979471},
{"learn":[0.000902187638],"iteration":412,"passed_time":16.97216217,"remaining_time":24.12266149},
{"learn":[0.0009002456442],"iteration":413,"passed_time":16.99983118,"remaining_time":24.06256297},
{"learn":[0.0008969800547],"iteration":414,"passed_time":17.03753701,"remaining_time":24.01676904},
{"learn":[0.0008954836677],"iteration":415,"passed_time":17.09701509,"remaining_time":24.00157888},
{"learn":[0.0008935820311],"iteration":416,"passed_time":17.14087776,"remaining_time":23.96434468},
{"learn":[0.0008920201411],"iteration":417,"passed_time":17.19758241,"remaining_time":23.94495923},
{"learn":[0.0008902537326],"iteration":418,"passed_time":17.22339844,"remaining_time":23.88256443},
{"learn":[0.0008888768653],"iteration":419,"passed_time":17.28916652,"remaining_time":23.87551567},
{"learn":[0.0008861339341],"iteration":420,"passed_time":17.32637179,"remaining_time":23.82890563},
{"learn":[0.0008821152151],"iteration":421,"passed_time":17.36324723,"remaining_time":23.78188838},
{"learn":[0.0008806257819],"iteration":422,"passed_time":17.40357071,"remaining_time":23.73962246},
{"learn":[0.000878463313],"iteration":423,"passed_time":17.43594452,"remaining_time":23.68656614},
{"learn":[0.000876033927],"iteration":424,"passed_time":17.45986539,"remaining_time":23.62217082},
{"learn":[0.0008743134017],"iteration":425,"passed_time":17.51540417,"remaining_time":23.60056807},
{"learn":[0.0008719496429],"iteration":426,"passed_time":17.53872817,"remaining_time":23.53557668},
{"learn":[0.0008696830521],"iteration":427,"passed_time":17.56180741,"remaining_time":23.47045289},
{"learn":[0.0008671519657],"iteration":428,"passed_time":17.59165353,"remaining_time":23.41453186},
{"learn":[0.0008656731496],"iteration":429,"passed_time":17.62599837,"remaining_time":23.36469552},
{"learn":[0.0008633674433],"iteration":430,"passed_time":17.65627894,"remaining_time":23.30956546},
{"learn":[0.0008617416024],"iteration":431,"passed_time":17.72597561,"remaining_time":23.30637534},
{"learn":[0.000860047775],"iteration":432,"passed_time":17.75159257,"remaining_time":23.24515701},
{"learn":[0.0008562394728],"iteration":433,"passed_time":17.77640178,"remaining_time":23.18304932},
{"learn":[0.0008534514035],"iteration":434,"passed_time":17.81335147,"remaining_time":23.13688179},
{"learn":[0.0008512097721],"iteration":435,"passed_time":17.84197447,"remaining_time":23.07998533},
{"learn":[0.0008485957359],"iteration":436,"passed_time":17.88720638,"remaining_time":23.044616},
{"learn":[0.0008468361571],"iteration":437,"passed_time":17.94115836,"remaining_time":23.0203904},
{"learn":[0.0008452444027],"iteration":438,"passed_time":17.99811245,"remaining_time":22.99986579},
{"learn":[0.0008436230322],"iteration":439,"passed_time":18.05254912,"remaining_time":22.9759716},
{"learn":[0.0008423339576],"iteration":440,"passed_time":18.10763588,"remaining_time":22.95276294},
{"learn":[0.0008410980304],"iteration":441,"passed_time":18.16155245,"remaining_time":22.92793274},
{"learn":[0.0008387024825],"iteration":442,"passed_time":18.19505202,"remaining_time":22.87730017},
{"learn":[0.0008350881437],"iteration":443,"passed_time":18.22812074,"remaining_time":22.82620525},
{"learn":[0.0008332482229],"iteration":444,"passed_time":18.26539166,"remaining_time":22.7804323},
{"learn":[0.0008315501114],"iteration":445,"passed_time":18.29083396,"remaining_time":22.72000451},
{"learn":[0.0008301099141],"iteration":446,"passed_time":18.34990513,"remaining_time":22.70133677},
{"learn":[0.0008284108092],"iteration":447,"passed_time":18.37335307,"remaining_time":22.63859575},
{"learn":[0.000826684696],"iteration":448,"passed_time":18.42219907,"remaining_time":22.60719753},
{"learn":[0.000825286222],"iteration":449,"passed_time":18.48410413,"remaining_time":22.59168283},
{"learn":[0.0008237181231],"iteration":450,"passed_time":18.5404242,"remaining_time":22.56916382},
{"learn":[0.0008218667159],"iteration":451,"passed_time":18.59555329,"remaining_time":22.54505133},
{"learn":[0.0008195329458],"iteration":452,"passed_time":18.63837927,"remaining_time":22.50594583},
{"learn":[0.0008179763953],"iteration":453,"passed_time":18.66242252,"remaining_time":22.44423502},
{"learn":[0.0008165204277],"iteration":454,"passed_time":18.71646804,"remaining_time":22.41862655},
{"learn":[0.0008150572578],"iteration":455,"passed_time":18.77073916,"remaining_time":22.39316251},
{"learn":[0.0008133189132],"iteration":456,"passed_time":18.81221711,"remaining_time":22.35237176},
{"learn":[0.0008117927238],"iteration":457,"passed_time":18.86274866,"remaining_time":22.32229208},
{"learn":[0.0008100202928],"iteration":458,"passed_time":18.9210736,"remaining_time":22.30130897},
{"learn":[0.0008082030962],"iteration":459,"passed_time":18.96812286,"remaining_time":22.26692684},
{"learn":[0.0008062958096],"iteration":460,"passed_time":18.9941779,"remaining_time":22.20794336},
{"learn":[0.0008047344163],"iteration":461,"passed_time":19.01985024,"remaining_time":22.14865677},
{"learn":[0.0008036755025],"iteration":462,"passed_time":19.08396812,"remaining_time":22.13410557},
{"learn":[0.000802492847],"iteration":463,"passed_time":19.1140493,"remaining_time":22.08002246},
{"learn":[0.0008007771646],"iteration":464,"passed_time":19.1597455,"remaining_time":22.04400826},
{"learn":[0.0007992615302],"iteration":465,"passed_time":19.21954489,"remaining_time":22.02411367},
{"learn":[0.0007979270071],"iteration":466,"passed_time":19.28294848,"remaining_time":22.00816176},
{"learn":[0.0007962082823],"iteration":467,"passed_time":19.33469321,"remaining_time":21.97875382},
{"learn":[0.0007949661463],"iteration":468,"passed_time":19.38086766,"remaining_time":21.94294399},
{"learn":[0.000793780759],"iteration":469,"passed_time":19.44020129,"remaining_time":21.92192912},
{"learn":[0.0007917840034],"iteration":470,"passed_time":19.46444235,"remaining_time":21.86133758},
{"learn":[0.0007903687656],"iteration":471,"passed_time":19.52686988,"remaining_time":21.84361716},
{"learn":[0.0007871117443],"iteration":472,"passed_time":19.55761395,"remaining_time":21.79040709},
{"learn":[0.0007857978965],"iteration":473,"passed_time":19.62160999,"remaining_time":21.77419168},
{"learn":[0.0007844882707],"iteration":474,"passed_time":19.6842185,"remaining_time":21.7562415},
{"learn":[0.0007829622676],"iteration":475,"passed_time":19.7094485,"remaining_time":21.69695591},
{"learn":[0.0007820176582],"iteration":476,"passed_time":19.76857748,"remaining_time":21.67498118},
{"learn":[0.0007803260038],"iteration":477,"passed_time":19.83091536,"remaining_time":21.65635526},
{"learn":[0.0007789110144],"iteration":478,"passed_time":19.89186861,"remaining_time":21.63604081},
{"learn":[0.0007772477344],"iteration":479,"passed_time":19.93498076,"remaining_time":21.59622916},
{"learn":[0.0007753179098],"iteration":480,"passed_time":19.95807083,"remaining_time":21.53479992},
{"learn":[0.0007740097741],"iteration":481,"passed_time":19.98418237,"remaining_time":21.47677691},
{"learn":[0.0007711142302],"iteration":482,"passed_time":20.00746591,"remaining_time":21.41585895},
{"learn":[0.0007692145805],"iteration":483,"passed_time":20.03093945,"remaining_time":21.35529908},
{"learn":[0.0007680381959],"iteration":484,"passed_time":20.09362898,"remaining_time":21.33653386},
{"learn":[0.0007662100097],"iteration":485,"passed_time":20.11797919,"remaining_time":21.27703972},
{"learn":[0.0007637610038],"iteration":486,"passed_time":20.14910871,"remaining_time":21.22483115},
{"learn":[0.0007607938101],"iteration":487,"passed_time":20.17422028,"remaining_time":21.16639504},
{"learn":[0.0007599259416],"iteration":488,"passed_time":20.23760191,"remaining_time":21.14808707},
{"learn":[0.0007571308563],"iteration":489,"passed_time":20.26783101,"remaining_time":21.09508942},
{"learn":[0.0007559403777],"iteration":490,"passed_time":20.3349349,"remaining_time":21.08041113},
{"learn":[0.0007546122496],"iteration":491,"passed_time":20.36367705,"remaining_time":21.02591045},
{"learn":[0.00075346188],"iteration":492,"passed_time":20.39480441,"remaining_time":20.97396721},
{"learn":[0.0007522801558],"iteration":493,"passed_time":20.45549368,"remaining_time":20.95238826},
{"learn":[0.000751338775],"iteration":494,"passed_time":20.5130154,"remaining_time":20.92741976},
{"learn":[0.000749979727],"iteration":495,"passed_time":20.57602123,"remaining_time":20.90789254},
{"learn":[0.0007488554964],"iteration":496,"passed_time":20.59843123,"remaining_time":20.84710444},
{"learn":[0.0007460212956],"iteration":497,"passed_time":20.62342594,"remaining_time":20.78907595},
{"learn":[0.0007431733112],"iteration":498,"passed_time":20.65263246,"remaining_time":20.73540854},
{"learn":[0.0007404890532],"iteration":499,"passed_time":20.67629441,"remaining_time":20.67629441},
{"learn":[0.00073935166],"iteration":500,"passed_time":20.72067672,"remaining_time":20.63795945},
{"learn":[0.0007380301133],"iteration":501,"passed_time":20.74514286,"remaining_time":20.57984292},
{"learn":[0.0007368483891],"iteration":502,"passed_time":20.77053027,"remaining_time":20.52277047},
{"learn":[0.0007356161252],"iteration":503,"passed_time":20.83007695,"remaining_time":20.49944081},
{"learn":[0.0007343854134],"iteration":504,"passed_time":20.85568502,"remaining_time":20.44270115},
{"learn":[0.0007336235295],"iteration":505,"passed_time":20.91343946,"remaining_time":20.41746856},
{"learn":[0.000731981794],"iteration":506,"passed_time":20.97076456,"remaining_time":20.39169019},
{"learn":[0.0007301554705],"iteration":507,"passed_time":21.00677247,"remaining_time":20.34514184},
{"learn":[0.0007289790859],"iteration":508,"passed_time":21.06569294,"remaining_time":20.32073719},
{"learn":[0.0007278706878],"iteration":509,"passed_time":21.12413789,"remaining_time":20.29574032},
{"learn":[0.0007266048342],"iteration":510,"passed_time":21.18420125,"remaining_time":20.27216127},
{"learn":[0.0007254997889],"iteration":511,"passed_time":21.24248716,"remaining_time":20.24674558},
{"learn":[0.0007243044674],"iteration":512,"passed_time":21.26760494,"remaining_time":20.18971463},
{"learn":[0.0007234177863],"iteration":513,"passed_time":21.32558221,"remaining_time":20.16387734},
{"learn":[0.0007225632668],"iteration":514,"passed_time":21.38248848,"remaining_time":20.13690663},
{"learn":[0.0007209626337],"iteration":515,"passed_time":21.4066883,"remaining_time":20.07914174},
{"learn":[0.0007188708832],"iteration":516,"passed_time":21.44234595,"remaining_time":20.03221101},
{"learn":[0.0007163890948],"iteration":517,"passed_time":21.46723226,"remaining_time":19.97530106},
{"learn":[0.0007142518957],"iteration":518,"passed_time":21.50217303,"remaining_time":19.9278328},
{"learn":[0.0007132786016],"iteration":519,"passed_time":21.5598695,"remaining_time":19.901418},
{"learn":[0.0007120496283],"iteration":520,"passed_time":21.5851177,"remaining_time":19.84505063},
{"learn":[0.0007109595463],"iteration":521,"passed_time":21.60930829,"remaining_time":19.78783403},
{"learn":[0.0007084501286],"iteration":522,"passed_time":21.63364827,"remaining_time":19.73087997},
{"learn":[0.0007062527041],"iteration":523,"passed_time":21.66894819,"remaining_time":19.68400637},
{"learn":[0.0007048455377],"iteration":524,"passed_time":21.69239676,"remaining_time":19.62645422},
{"learn":[0.0007035724819],"iteration":525,"passed_time":21.71733367,"remaining_time":19.57037293},
{"learn":[0.0007012557238],"iteration":526,"passed_time":21.74509577,"remaining_time":19.51694554},
{"learn":[0.0006996550287],"iteration":527,"passed_time":21.76993407,"remaining_time":19.46100167},
{"learn":[0.0006986819208],"iteration":528,"passed_time":21.82959058,"remaining_time":19.43617611},
{"learn":[0.00069630829],"iteration":529,"passed_time":21.85249785,"remaining_time":19.37863017},
{"learn":[0.0006952488174],"iteration":530,"passed_time":21.91096033,"remaining_time":19.35261845},
{"learn":[0.0006934927156],"iteration":531,"passed_time":21.94665756,"remaining_time":19.30645815},
{"learn":[0.0006913128619],"iteration":532,"passed_time":21.97526814,"remaining_time":19.25412799},
{"learn":[0.0006888990601],"iteration":533,"passed_time":22.00055844,"remaining_time":19.1989892},
{"learn":[0.0006864584982],"iteration":534,"passed_time":22.02913343,"remaining_time":19.14681691},
{"learn":[0.0006856150925],"iteration":535,"passed_time":22.08786884,"remaining_time":19.12084169},
{"learn":[0.0006846123685],"iteration":536,"passed_time":22.14951625,"remaining_time":19.09725517},
{"learn":[0.0006832882762],"iteration":537,"passed_time":22.17547389,"remaining_time":19.04287906},
{"learn":[0.0006818975632],"iteration":538,"passed_time":22.23436433,"remaining_time":19.01677543},
{"learn":[0.0006809915726],"iteration":539,"passed_time":22.29882118,"remaining_time":18.99529211},
{"learn":[0.0006799807772],"iteration":540,"passed_time":22.3613537,"remaining_time":18.97201728},
{"learn":[0.0006791248297],"iteration":541,"passed_time":22.42011878,"remaining_time":18.94541402},
{"learn":[0.0006780199707],"iteration":542,"passed_time":22.44503641,"remaining_time":18.89020559},
{"learn":[0.0006764060507],"iteration":543,"passed_time":22.49039132,"remaining_time":18.85223979},
{"learn":[0.0006748729696],"iteration":544,"passed_time":22.52579791,"remaining_time":18.80594137},
{"learn":[0.0006738228103],"iteration":545,"passed_time":22.58566052,"remaining_time":18.78001809},
{"learn":[0.0006728631755],"iteration":546,"passed_time":22.60983313,"remaining_time":18.72441391},
{"learn":[0.0006719144682],"iteration":547,"passed_time":22.66926641,"remaining_time":18.69800806},
{"learn":[0.0006710877642],"iteration":548,"passed_time":22.72672655,"remaining_time":18.66986097},
{"learn":[0.0006697033842],"iteration":549,"passed_time":22.75161549,"remaining_time":18.61495813},
{"learn":[0.0006686646491],"iteration":550,"passed_time":22.81099764,"remaining_time":18.58827213},
{"learn":[0.000667621692],"iteration":551,"passed_time":22.87102525,"remaining_time":18.5619915},
{"learn":[0.0006663647791],"iteration":552,"passed_time":22.89569226,"remaining_time":18.50700622},
{"learn":[0.0006654726962],"iteration":553,"passed_time":22.95434701,"remaining_time":18.47949236},
{"learn":[0.0006644532084],"iteration":554,"passed_time":22.97887075,"remaining_time":18.42449997},
{"learn":[0.0006624403099],"iteration":555,"passed_time":23.01200326,"remaining_time":18.37649181},
{"learn":[0.0006601581971],"iteration":556,"passed_time":23.03560629,"remaining_time":18.32095796},
{"learn":[0.0006580431014],"iteration":557,"passed_time":23.05971991,"remaining_time":18.26594301},
{"learn":[0.0006570679446],"iteration":558,"passed_time":23.1205639,"remaining_time":18.24001552},
{"learn":[0.0006558321416],"iteration":559,"passed_time":23.16663241,"remaining_time":18.20235404},
{"learn":[0.0006547196458],"iteration":560,"passed_time":23.22574931,"remaining_time":18.17487335},
{"learn":[0.0006532330066],"iteration":561,"passed_time":23.26514354,"remaining_time":18.13190902},
{"learn":[0.0006522310277],"iteration":562,"passed_time":23.32317285,"remaining_time":18.10342191},
{"learn":[0.0006511976322],"iteration":563,"passed_time":23.34804054,"remaining_time":18.04919446},
{"learn":[0.0006502652541],"iteration":564,"passed_time":23.37154925,"remaining_time":17.99402465},
{"learn":[0.0006488967066],"iteration":565,"passed_time":23.39679633,"remaining_time":17.94029966},
{"learn":[0.000647866043],"iteration":566,"passed_time":23.42417019,"remaining_time":17.88829928},
{"learn":[0.0006470802551],"iteration":567,"passed_time":23.48380843,"remaining_time":17.86092472},
{"learn":[0.0006458578631],"iteration":568,"passed_time":23.50906386,"remaining_time":17.80739283},
{"learn":[0.0006451571981],"iteration":569,"passed_time":23.570849,"remaining_time":17.78151766},
{"learn":[0.0006438026826],"iteration":570,"passed_time":23.6204507,"remaining_time":17.74636313},
{"learn":[0.000642836156],"iteration":571,"passed_time":23.68192741,"remaining_time":17.72004359},
{"learn":[0.0006421669697],"iteration":572,"passed_time":23.74337116,"remaining_time":17.69357676},
{"learn":[0.0006411399692],"iteration":573,"passed_time":23.80531662,"remaining_time":17.66736042},
{"learn":[0.0006394763788],"iteration":574,"passed_time":23.83658611,"remaining_time":17.61834625},
{"learn":[0.0006386697913],"iteration":575,"passed_time":23.89993854,"remaining_time":17.59301031},
{"learn":[0.0006376833344],"iteration":576,"passed_time":23.96123176,"remaining_time":17.56603299},
{"learn":[0.0006362119069],"iteration":577,"passed_time":24.00655346,"remaining_time":17.52727606},
{"learn":[0.0006351053715],"iteration":578,"passed_time":24.05205821,"remaining_time":17.48862955},
{"learn":[0.0006339521458],"iteration":579,"passed_time":24.07792035,"remaining_time":17.43573542},
{"learn":[0.0006330656509],"iteration":580,"passed_time":24.10592553,"remaining_time":17.38447986},
{"learn":[0.0006322084616],"iteration":581,"passed_time":24.1311198,"remaining_time":17.33128536},
{"learn":[0.0006313084314],"iteration":582,"passed_time":24.1904568,"remaining_time":17.30260804},
{"learn":[0.0006304019441],"iteration":583,"passed_time":24.25800496,"remaining_time":17.27967476},
{"learn":[0.0006293031077],"iteration":584,"passed_time":24.30748956,"remaining_time":17.24377464},
{"learn":[0.0006281535452],"iteration":585,"passed_time":24.33336427,"remaining_time":17.19114814},
{"learn":[0.0006273935859],"iteration":586,"passed_time":24.39491887,"remaining_time":17.16371635},
{"learn":[0.000626553533],"iteration":587,"passed_time":24.45704137,"remaining_time":17.1365664},
{"learn":[0.0006256686524],"iteration":588,"passed_time":24.51976062,"remaining_time":17.10971412},
{"learn":[0.0006245762731],"iteration":589,"passed_time":24.546516,"remaining_time":17.05774841},
{"learn":[0.0006233500938],"iteration":590,"passed_time":24.57121353,"remaining_time":17.00444388},
{"learn":[0.0006225258112],"iteration":591,"passed_time":24.6343926,"remaining_time":16.97775706},
{"learn":[0.0006216696153],"iteration":592,"passed_time":24.69928279,"remaining_time":16.95212158},
{"learn":[0.0006208196282],"iteration":593,"passed_time":24.7628308,"remaining_time":16.92543654},
{"learn":[0.0006191955258],"iteration":594,"passed_time":24.79263907,"remaining_time":16.87566189},
{"learn":[0.0006181587776],"iteration":595,"passed_time":24.82902022,"remaining_time":16.83040968},
{"learn":[0.0006172776222],"iteration":596,"passed_time":24.89063693,"remaining_time":16.80222225},
{"learn":[0.0006164887299],"iteration":597,"passed_time":24.95185836,"remaining_time":16.77365729},
{"learn":[0.0006155837327],"iteration":598,"passed_time":25.01391567,"remaining_time":16.74554287},
{"learn":[0.0006136527906],"iteration":599,"passed_time":25.04372844,"remaining_time":16.69581896},
{"learn":[0.0006128401806],"iteration":600,"passed_time":25.10307326,"remaining_time":16.66576744},
{"learn":[0.0006117994587],"iteration":601,"passed_time":25.14625031,"remaining_time":16.62492961},
{"learn":[0.0006109421452],"iteration":602,"passed_time":25.20643304,"remaining_time":16.59528013},
{"learn":[0.0006101011609],"iteration":603,"passed_time":25.26654152,"remaining_time":16.56548087},
{"learn":[0.0006089352692],"iteration":604,"passed_time":25.30135862,"remaining_time":16.51906885},
{"learn":[0.0006075240672],"iteration":605,"passed_time":25.33163362,"remaining_time":16.46974199},
{"learn":[0.0006068985909],"iteration":606,"passed_time":25.39079758,"remaining_time":16.43918196},
{"learn":[0.0006058417261],"iteration":607,"passed_time":25.44969492,"remaining_time":16.40835594},
{"learn":[0.0006050971026],"iteration":608,"passed_time":25.51178127,"remaining_time":16.37948518},
{"learn":[0.0006045199931],"iteration":609,"passed_time":25.57068339,"remaining_time":16.34846971},
{"learn":[0.000603843232],"iteration":610,"passed_time":25.63349469,"remaining_time":16.31985178},
{"learn":[0.0006032283107],"iteration":611,"passed_time":25.69295905,"remaining_time":16.28900018},
{"learn":[0.0006025640915],"iteration":612,"passed_time":25.75324544,"remaining_time":16.2585742},
{"learn":[0.0006015501916],"iteration":613,"passed_time":25.77781509,"remaining_time":16.20559711},
{"learn":[0.0006006689121],"iteration":614,"passed_time":25.80465276,"remaining_time":16.15413221},
{"learn":[0.0005995329469],"iteration":615,"passed_time":25.83093071,"remaining_time":16.10239837},
{"learn":[0.0005988962327],"iteration":616,"passed_time":25.89184118,"remaining_time":16.07224501},
{"learn":[0.000598182405],"iteration":617,"passed_time":25.95159867,"remaining_time":16.04127944},
{"learn":[0.000597309197],"iteration":618,"passed_time":26.01276663,"remaining_time":16.01108899},
{"learn":[0.0005964533115],"iteration":619,"passed_time":26.06964045,"remaining_time":15.97816673},
{"learn":[0.0005949279914],"iteration":620,"passed_time":26.09670016,"remaining_time":15.92697159},
{"learn":[0.0005940948923],"iteration":621,"passed_time":26.12165268,"remaining_time":15.87457349},
{"learn":[0.0005930629248],"iteration":622,"passed_time":26.17529398,"remaining_time":15.83962413},
{"learn":[0.000592266582],"iteration":623,"passed_time":26.23230644,"remaining_time":15.80664619},
{"learn":[0.0005913163225],"iteration":624,"passed_time":26.25712948,"remaining_time":15.75427769},
{"learn":[0.0005895396695],"iteration":625,"passed_time":26.2902229,"remaining_time":15.70693828},
{"learn":[0.0005887883405],"iteration":626,"passed_time":26.37503388,"remaining_time":15.69041091},
{"learn":[0.0005879847954],"iteration":627,"passed_time":26.43271356,"remaining_time":15.65759466},
{"learn":[0.0005872495472],"iteration":628,"passed_time":26.45635334,"remaining_time":15.60462176},
{"learn":[0.0005862063418],"iteration":629,"passed_time":26.47925211,"remaining_time":15.5513068},
{"learn":[0.0005852887407],"iteration":630,"passed_time":26.53629932,"remaining_time":15.51805777},
{"learn":[0.0005837062995],"iteration":631,"passed_time":26.56036634,"remaining_time":15.46552977},
{"learn":[0.0005828052759],"iteration":632,"passed_time":26.58307966,"remaining_time":15.41230685},
{"learn":[0.0005821208159],"iteration":633,"passed_time":26.63832288,"remaining_time":15.37795927},
{"learn":[0.0005812361836],"iteration":634,"passed_time":26.6932088,"remaining_time":15.34334049},
{"learn":[0.0005805063993],"iteration":635,"passed_time":26.74733846,"remaining_time":15.30822516},
{"learn":[0.0005797227224],"iteration":636,"passed_time":26.77013469,"remaining_time":15.2551945},
{"learn":[0.0005789867292],"iteration":637,"passed_time":26.82513215,"remaining_time":15.22052953},
{"learn":[0.0005777201926],"iteration":638,"passed_time":26.85876756,"remaining_time":15.17373254},
{"learn":[0.0005770964548],"iteration":639,"passed_time":26.88207403,"remaining_time":15.12116664},
{"learn":[0.0005758609002],"iteration":640,"passed_time":26.9162966,"remaining_time":15.07480574},
{"learn":[0.0005751469483],"iteration":641,"passed_time":26.97180448,"remaining_time":15.04035203},
{"learn":[0.0005734760314],"iteration":642,"passed_time":27.00553585,"remaining_time":14.9937423},
{"learn":[0.0005721352994],"iteration":643,"passed_time":27.0399081,"remaining_time":14.94752684},
{"learn":[0.0005714786549],"iteration":644,"passed_time":27.09548696,"remaining_time":14.91301995},
{"learn":[0.0005707114935],"iteration":645,"passed_time":27.11802906,"remaining_time":14.8603441},
{"learn":[0.0005701681599],"iteration":646,"passed_time":27.14534766,"remaining_time":14.81036742},
{"learn":[0.0005694177623],"iteration":647,"passed_time":27.16773131,"remaining_time":14.75777997},
{"learn":[0.0005686569959],"iteration":648,"passed_time":27.2228819,"remaining_time":14.72300701},
{"learn":[0.0005679838359],"iteration":649,"passed_time":27.27838018,"remaining_time":14.68835856},
{"learn":[0.0005672058711],"iteration":650,"passed_time":27.30139435,"remaining_time":14.63623138},
{"learn":[0.0005657768498],"iteration":651,"passed_time":27.32646373,"remaining_time":14.58529046},
{"learn":[0.0005641410748],"iteration":652,"passed_time":27.35222593,"remaining_time":14.53479694},
{"learn":[0.0005628138781],"iteration":653,"passed_time":27.38388122,"remaining_time":14.48749679},
{"learn":[0.0005623711894],"iteration":654,"passed_time":27.45017033,"remaining_time":14.45848666},
{"learn":[0.0005616569271],"iteration":655,"passed_time":27.51084121,"remaining_time":14.42641673},
{"learn":[0.0005608218412],"iteration":656,"passed_time":27.57298755,"remaining_time":14.39503003},
{"learn":[0.0005601526548],"iteration":657,"passed_time":27.63655988,"remaining_time":14.364291},
{"learn":[0.0005587385346],"iteration":658,"passed_time":27.66574818,"remaining_time":14.31566029},
{"learn":[0.0005578763162],"iteration":659,"passed_time":27.72524749,"remaining_time":14.28270325},
{"learn":[0.000557317088],"iteration":660,"passed_time":27.78868297,"remaining_time":14.25168461},
{"learn":[0.0005559994529],"iteration":661,"passed_time":27.82109767,"remaining_time":14.20472963},
{"learn":[0.0005552982291],"iteration":662,"passed_time":27.89296,"remaining_time":14.17786956},
{"learn":[0.0005547233547],"iteration":663,"passed_time":27.95497985,"remaining_time":14.14589342},
{"learn":[0.0005540138111],"iteration":664,"passed_time":27.98245695,"remaining_time":14.09642568},
{"learn":[0.0005535310134],"iteration":665,"passed_time":28.04498972,"remaining_time":14.06460446},
{"learn":[0.0005528985833],"iteration":666,"passed_time":28.10766822,"remaining_time":14.0327639},
{"learn":[0.000551811792],"iteration":667,"passed_time":28.14333373,"remaining_time":13.98740539},
{"learn":[0.0005511158456],"iteration":668,"passed_time":28.20633881,"remaining_time":13.95560261},
{"learn":[0.0005506251628],"iteration":669,"passed_time":28.27080748,"remaining_time":13.92442757},
{"learn":[0.0005497931192],"iteration":670,"passed_time":28.33196205,"remaining_time":13.89152834},
{"learn":[0.0005491026988],"iteration":671,"passed_time":28.39442517,"remaining_time":13.85918371},
{"learn":[0.0005479394148],"iteration":672,"passed_time":28.42509886,"remaining_time":13.81130361},
{"learn":[0.0005472766856],"iteration":673,"passed_time":28.45050694,"remaining_time":13.76092769},
{"learn":[0.0005465938399],"iteration":674,"passed_time":28.51144864,"remaining_time":13.72773453},
{"learn":[0.0005459107459],"iteration":675,"passed_time":28.57487651,"remaining_time":13.69565087},
{"learn":[0.000545170779],"iteration":676,"passed_time":28.59673349,"remaining_time":13.64364094},
{"learn":[0.0005443139002],"iteration":677,"passed_time":28.62431324,"remaining_time":13.59443785},
{"learn":[0.0005428522825],"iteration":678,"passed_time":28.65459868,"remaining_time":13.54657758},
{"learn":[0.0005413873742],"iteration":679,"passed_time":28.68420422,"remaining_time":13.49844904},
{"learn":[0.000540860494],"iteration":680,"passed_time":28.74105036,"remaining_time":13.46313519},
{"learn":[0.0005403989305],"iteration":681,"passed_time":28.79730084,"remaining_time":13.42748045},
{"learn":[0.0005397116144],"iteration":682,"passed_time":28.85806508,"remaining_time":13.39386037},
{"learn":[0.0005390801777],"iteration":683,"passed_time":28.91879531,"remaining_time":13.3601452},
{"learn":[0.0005381584167],"iteration":684,"passed_time":28.94238553,"remaining_time":13.30927218},
{"learn":[0.0005369111275],"iteration":685,"passed_time":28.97498895,"remaining_time":13.26260427},
{"learn":[0.0005356828372],"iteration":686,"passed_time":29.00490738,"remaining_time":13.21475402},
{"learn":[0.0005351357783],"iteration":687,"passed_time":29.06451843,"remaining_time":13.18042115},
{"learn":[0.0005342766643],"iteration":688,"passed_time":29.08802071,"remaining_time":13.12971617},
{"learn":[0.0005335142215],"iteration":689,"passed_time":29.14997457,"remaining_time":13.09636539},
{"learn":[0.000532848388],"iteration":690,"passed_time":29.17631156,"remaining_time":13.04700474},
{"learn":[0.0005315395693],"iteration":691,"passed_time":29.20663717,"remaining_time":12.99948591},
{"learn":[0.0005300372839],"iteration":692,"passed_time":29.23659054,"remaining_time":12.9518518},
{"learn":[0.0005292793115],"iteration":693,"passed_time":29.29695067,"remaining_time":12.91767566},
{"learn":[0.0005280031512],"iteration":694,"passed_time":29.32351096,"remaining_time":12.86859114},
{"learn":[0.0005273584276],"iteration":695,"passed_time":29.34823053,"remaining_time":12.81876736},
{"learn":[0.0005264846608],"iteration":696,"passed_time":29.37122023,"remaining_time":12.7682636},
{"learn":[0.000525889049],"iteration":697,"passed_time":29.43185214,"remaining_time":12.73412514},
{"learn":[0.000524609598],"iteration":698,"passed_time":29.45436272,"remaining_time":12.68349525},
{"learn":[0.0005234640092],"iteration":699,"passed_time":29.48332573,"remaining_time":12.63571103},
{"learn":[0.0005225937814],"iteration":700,"passed_time":29.51192578,"remaining_time":12.58782569},
{"learn":[0.0005218380441],"iteration":701,"passed_time":29.57120511,"remaining_time":12.55301869},
{"learn":[0.0005205509563],"iteration":702,"passed_time":29.59885386,"remaining_time":12.50477894},
{"learn":[0.0005197910592],"iteration":703,"passed_time":29.65913,"remaining_time":12.47031602},
{"learn":[0.0005184186623],"iteration":704,"passed_time":29.69204243,"remaining_time":12.42432981},
{"learn":[0.0005173253827],"iteration":705,"passed_time":29.72059576,"remaining_time":12.37656537},
{"learn":[0.0005159197375],"iteration":706,"passed_time":29.74613843,"remaining_time":12.32760758},
{"learn":[0.0005153864622],"iteration":707,"passed_time":29.77337578,"remaining_time":12.27941487},
{"learn":[0.0005147298177],"iteration":708,"passed_time":29.83906436,"remaining_time":12.24706309},
{"learn":[0.0005138648674],"iteration":709,"passed_time":29.88541767,"remaining_time":12.20671989},
{"learn":[0.0005131436512],"iteration":710,"passed_time":29.94663374,"remaining_time":12.17240106},
{"learn":[0.0005118373161],"iteration":711,"passed_time":29.97052951,"remaining_time":12.12291081},
{"learn":[0.0005112124917],"iteration":712,"passed_time":30.03229549,"remaining_time":12.08873605},
{"learn":[0.0005106778195],"iteration":713,"passed_time":30.05706146,"remaining_time":12.03966327},
{"learn":[0.0005093996723],"iteration":714,"passed_time":30.08577724,"remaining_time":11.99223288},
{"learn":[0.0005086739237],"iteration":715,"passed_time":30.11187643,"remaining_time":11.94381691},
{"learn":[0.0005078980699],"iteration":716,"passed_time":30.17046542,"remaining_time":11.90828691},
{"learn":[0.0005065481489],"iteration":717,"passed_time":30.19998564,"remaining_time":11.8612757},
{"learn":[0.0005057197064],"iteration":718,"passed_time":30.22504901,"remaining_time":11.81257131},
{"learn":[0.0005052713367],"iteration":719,"passed_time":30.253587,"remaining_time":11.76528384},
{"learn":[0.000504618076],"iteration":720,"passed_time":30.312347,"remaining_time":11.72974315},
{"learn":[0.0005041637768],"iteration":721,"passed_time":30.33594401,"remaining_time":11.68059894},
{"learn":[0.0005036542192],"iteration":722,"passed_time":30.36142208,"remaining_time":11.63224608},
{"learn":[0.0005029992821],"iteration":723,"passed_time":30.38647175,"remaining_time":11.5837931},
{"learn":[0.000502466814],"iteration":724,"passed_time":30.44853296,"remaining_time":11.54944354},
{"learn":[0.0005022277435],"iteration":725,"passed_time":30.50964638,"remaining_time":11.51465993},
{"learn":[0.0005013535731],"iteration":726,"passed_time":30.55338888,"remaining_time":11.47328083},
{"learn":[0.0005008511245],"iteration":727,"passed_time":30.57962701,"remaining_time":11.42535515},
{"learn":[0.0004995061085],"iteration":728,"passed_time":30.60701908,"remaining_time":11.37791793},
{"learn":[0.0004990730435],"iteration":729,"passed_time":30.63162303,"remaining_time":11.32950441},
{"learn":[0.0004983562045],"iteration":730,"passed_time":30.69008043,"remaining_time":11.29361373},
{"learn":[0.0004971880776],"iteration":731,"passed_time":30.72499841,"remaining_time":11.24904313},
{"learn":[0.0004964503149],"iteration":732,"passed_time":30.76107618,"remaining_time":11.20492134},
{"learn":[0.0004960314992],"iteration":733,"passed_time":30.82236526,"remaining_time":11.16995798},
{"learn":[0.0004952369879],"iteration":734,"passed_time":30.84572598,"remaining_time":11.12124814},
{"learn":[0.0004946121325],"iteration":735,"passed_time":30.86906864,"remaining_time":11.07260071},
{"learn":[0.0004933531086],"iteration":736,"passed_time":30.89259259,"remaining_time":11.02408664},
{"learn":[0.0004921516404],"iteration":737,"passed_time":30.91993384,"remaining_time":10.97699548},
{"learn":[0.0004913659145],"iteration":738,"passed_time":30.97729719,"remaining_time":10.94056098},
{"learn":[0.0004905716206],"iteration":739,"passed_time":31.00252487,"remaining_time":10.89277901},
{"learn":[0.0004898915378],"iteration":740,"passed_time":31.03182164,"remaining_time":10.84648017},
{"learn":[0.0004886927394],"iteration":741,"passed_time":31.05652512,"remaining_time":10.79863003},
{"learn":[0.0004877371093],"iteration":742,"passed_time":31.08373711,"remaining_time":10.75170988},
{"learn":[0.0004870629559],"iteration":743,"passed_time":31.10820697,"remaining_time":10.70389917},
{"learn":[0.000486468027],"iteration":744,"passed_time":31.16813591,"remaining_time":10.66828813},
{"learn":[0.000486090531],"iteration":745,"passed_time":31.23197186,"remaining_time":10.63394216},
{"learn":[0.0004853236799],"iteration":746,"passed_time":31.29261599,"remaining_time":10.59843621},
{"learn":[0.0004851154362],"iteration":747,"passed_time":31.34968474,"remaining_time":10.56165849},
{"learn":[0.0004844922572],"iteration":748,"passed_time":31.37387683,"remaining_time":10.51380919},
{"learn":[0.0004839429011],"iteration":749,"passed_time":31.39669674,"remaining_time":10.46556558},
{"learn":[0.0004828969017],"iteration":750,"passed_time":31.42204249,"remaining_time":10.41822714},
{"learn":[0.0004822372769],"iteration":751,"passed_time":31.44538762,"remaining_time":10.37028741},
{"learn":[0.0004817018285],"iteration":752,"passed_time":31.50625736,"remaining_time":10.33472187},
{"learn":[0.0004812644795],"iteration":753,"passed_time":31.56566165,"remaining_time":10.29861109},
{"learn":[0.0004808502272],"iteration":754,"passed_time":31.6256776,"remaining_time":10.2626371},
{"learn":[0.0004804211358],"iteration":755,"passed_time":31.68389947,"remaining_time":10.22602046},
{"learn":[0.0004795281217],"iteration":756,"passed_time":31.72165405,"remaining_time":10.18277666},
{"learn":[0.0004788228621],"iteration":757,"passed_time":31.74720143,"remaining_time":10.13565006},
{"learn":[0.0004782983723],"iteration":758,"passed_time":31.80745162,"remaining_time":10.09959926},
{"learn":[0.000477784841],"iteration":759,"passed_time":31.83138494,"remaining_time":10.0520163},
{"learn":[0.0004773093077],"iteration":760,"passed_time":31.85708503,"remaining_time":10.00505036},
{"learn":[0.0004766576613],"iteration":761,"passed_time":31.88720665,"remaining_time":9.959521237},
{"learn":[0.0004755607496],"iteration":762,"passed_time":31.91570795,"remaining_time":9.913529205},
{"learn":[0.0004749599223],"iteration":763,"passed_time":31.9404138,"remaining_time":9.866410547},
{"learn":[0.0004746788492],"iteration":764,"passed_time":32.0011099,"remaining_time":9.830406309},
{"learn":[0.0004741960516],"iteration":765,"passed_time":32.06515641,"remaining_time":9.795361097},
{"learn":[0.0004730685304],"iteration":766,"passed_time":32.0953659,"remaining_time":9.749961219},
{"learn":[0.0004718419785],"iteration":767,"passed_time":32.12526928,"remaining_time":9.704508428},
{"learn":[0.0004713727782],"iteration":768,"passed_time":32.15117093,"remaining_time":9.657893999},
{"learn":[0.0004708903531],"iteration":769,"passed_time":32.20968121,"remaining_time":9.621073609},
{"learn":[0.0004703287346],"iteration":770,"passed_time":32.23452895,"remaining_time":9.574198612},
{"learn":[0.000469939597],"iteration":771,"passed_time":32.29338237,"remaining_time":9.537423809},
{"learn":[0.000469393221],"iteration":772,"passed_time":32.35338382,"remaining_time":9.500929013},
{"learn":[0.000468357342],"iteration":773,"passed_time":32.38449977,"remaining_time":9.455939208},
{"learn":[0.0004677921534],"iteration":774,"passed_time":32.41266473,"remaining_time":9.410128469},
{"learn":[0.0004670421282],"iteration":775,"passed_time":32.4457555,"remaining_time":9.365785094},
{"learn":[0.0004665832346],"iteration":776,"passed_time":32.47178021,"remaining_time":9.319442712},
{"learn":[0.0004662097432],"iteration":777,"passed_time":32.53078514,"remaining_time":9.28256337},
{"learn":[0.0004654558686],"iteration":778,"passed_time":32.55523782,"remaining_time":9.23582485},
{"learn":[0.000465055493],"iteration":779,"passed_time":32.57968875,"remaining_time":9.18914298},
{"learn":[0.0004646084892],"iteration":780,"passed_time":32.63913131,"remaining_time":9.152330035},
{"learn":[0.0004635526488],"iteration":781,"passed_time":32.66597406,"remaining_time":9.106371285},
{"learn":[0.0004625095986],"iteration":782,"passed_time":32.69924748,"remaining_time":9.062243553},
{"learn":[0.0004615204719],"iteration":783,"passed_time":32.72632887,"remaining_time":9.016437545},
{"learn":[0.0004608250844],"iteration":784,"passed_time":32.78540431,"remaining_time":8.979441945},
{"learn":[0.0004597437878],"iteration":785,"passed_time":32.81292677,"remaining_time":8.933799401},
{"learn":[0.0004594956835],"iteration":786,"passed_time":32.87233706,"remaining_time":8.896833282},
{"learn":[0.0004587943976],"iteration":787,"passed_time":32.92949669,"remaining_time":8.859204693},
{"learn":[0.0004582837845],"iteration":788,"passed_time":32.98934825,"remaining_time":8.82224649},
{"learn":[0.000457855314],"iteration":789,"passed_time":33.05109039,"remaining_time":8.78573289},
{"learn":[0.0004569801191],"iteration":790,"passed_time":33.07880871,"remaining_time":8.740165639},
{"learn":[0.0004562332605],"iteration":791,"passed_time":33.10452486,"remaining_time":8.694117641},
{"learn":[0.0004555936903],"iteration":792,"passed_time":33.12900034,"remaining_time":8.647797062},
{"learn":[0.0004544946675],"iteration":793,"passed_time":33.16098887,"remaining_time":8.603480739},
{"learn":[0.0004539016945],"iteration":794,"passed_time":33.18550808,"remaining_time":8.55726938},
{"learn":[0.0004534427697],"iteration":795,"passed_time":33.24478047,"remaining_time":8.520019117},
{"learn":[0.0004529673296],"iteration":796,"passed_time":33.30400546,"remaining_time":8.482701515},
{"learn":[0.0004526643703],"iteration":797,"passed_time":33.36374219,"remaining_time":8.44545855},
{"learn":[0.0004520804621],"iteration":798,"passed_time":33.38829672,"remaining_time":8.399308687},
{"learn":[0.0004514387498],"iteration":799,"passed_time":33.41813529,"remaining_time":8.354533822},
{"learn":[0.0004507752135],"iteration":800,"passed_time":33.4413268,"remaining_time":8.308144859},
{"learn":[0.0004503689085],"iteration":801,"passed_time":33.50012068,"remaining_time":8.270603361},
{"learn":[0.0004499598406],"iteration":802,"passed_time":33.56036107,"remaining_time":8.2333638},
{"learn":[0.0004494432981],"iteration":803,"passed_time":33.62173199,"remaining_time":8.196342625},
{"learn":[0.0004489187772],"iteration":804,"passed_time":33.68005249,"remaining_time":8.158522031},
{"learn":[0.0004484429955],"iteration":805,"passed_time":33.7044501,"remaining_time":8.112485508},
{"learn":[0.0004480377461],"iteration":806,"passed_time":33.76233262,"remaining_time":8.074510774},
{"learn":[0.0004470966756],"iteration":807,"passed_time":33.78662612,"remaining_time":8.028505216},
{"learn":[0.0004465132331],"iteration":808,"passed_time":33.81004336,"remaining_time":7.982346454},
{"learn":[0.0004462380583],"iteration":809,"passed_time":33.83535097,"remaining_time":7.936687265},
{"learn":[0.0004455784336],"iteration":810,"passed_time":33.89119735,"remaining_time":7.898195189},
{"learn":[0.0004450539127],"iteration":811,"passed_time":33.94894925,"remaining_time":7.86010155},
{"learn":[0.0004446092372],"iteration":812,"passed_time":34.00716325,"remaining_time":7.82206584},
{"learn":[0.0004441920047],"iteration":813,"passed_time":34.06763144,"remaining_time":7.784495637},
{"learn":[0.0004437479501],"iteration":814,"passed_time":34.12574769,"remaining_time":7.746335366},
{"learn":[0.0004433009463],"iteration":815,"passed_time":34.1602256,"remaining_time":7.70279597},
{"learn":[0.0004426185042],"iteration":816,"passed_time":34.19527631,"remaining_time":7.659407056},
{"learn":[0.0004421873949],"iteration":817,"passed_time":34.25416636,"remaining_time":7.621342638},
{"learn":[0.0004417599179],"iteration":818,"passed_time":34.31648919,"remaining_time":7.58398601},
{"learn":[0.0004413098097],"iteration":819,"passed_time":34.37901151,"remaining_time":7.546612284},
{"learn":[0.0004404824227],"iteration":820,"passed_time":34.42381729,"remaining_time":7.505314609},
{"learn":[0.0004400145262],"iteration":821,"passed_time":34.48412517,"remaining_time":7.467365304},
{"learn":[0.0004395259234],"iteration":822,"passed_time":34.50783817,"remaining_time":7.42149132},
{"learn":[0.0004390451747],"iteration":823,"passed_time":34.56712737,"remaining_time":7.383269923},
{"learn":[0.0004387990572],"iteration":824,"passed_time":34.62766735,"remaining_time":7.345262772},
{"learn":[0.0004379199197],"iteration":825,"passed_time":34.65729548,"remaining_time":7.300689362},
{"learn":[0.0004372507334],"iteration":826,"passed_time":34.71696225,"remaining_time":7.262435876},
{"learn":[0.0004361868526],"iteration":827,"passed_time":34.74102696,"remaining_time":7.216735069},
{"learn":[0.0004353356237],"iteration":828,"passed_time":34.77265138,"remaining_time":7.172645822},
{"learn":[0.0004350793237],"iteration":829,"passed_time":34.80053695,"remaining_time":7.127820821},
{"learn":[0.0004347694106],"iteration":830,"passed_time":34.82597212,"remaining_time":7.082538252},
{"learn":[0.0004340015352],"iteration":831,"passed_time":34.85282752,"remaining_time":7.037590172},
{"learn":[0.0004329192142],"iteration":832,"passed_time":34.87735671,"remaining_time":6.992219172},
{"learn":[0.0004324195286],"iteration":833,"passed_time":34.93548041,"remaining_time":6.953584829},
{"learn":[0.000431975505],"iteration":834,"passed_time":34.99805032,"remaining_time":6.915782399},
{"learn":[0.0004316658402],"iteration":835,"passed_time":35.06233572,"remaining_time":6.878257247},
{"learn":[0.0004312694694],"iteration":836,"passed_time":35.12045657,"remaining_time":6.839467648},
{"learn":[0.0004307598496],"iteration":837,"passed_time":35.17982627,"remaining_time":6.800873336},
{"learn":[0.0004305135148],"iteration":838,"passed_time":35.23846033,"remaining_time":6.762088335},
{"learn":[0.0004300625063],"iteration":839,"passed_time":35.27056814,"remaining_time":6.718203456},
{"learn":[0.0004293800332],"iteration":840,"passed_time":35.29975291,"remaining_time":6.673793952},
{"learn":[0.0004288366685],"iteration":841,"passed_time":35.363442,"remaining_time":6.635895293},
{"learn":[0.0004281167562],"iteration":842,"passed_time":35.39014788,"remaining_time":6.591047707},
{"learn":[0.0004274224862],"iteration":843,"passed_time":35.41682449,"remaining_time":6.546237702},
{"learn":[0.0004264480124],"iteration":844,"passed_time":35.43945895,"remaining_time":6.500729156},
{"learn":[0.0004259267201],"iteration":845,"passed_time":35.49616417,"remaining_time":6.461476693},
{"learn":[0.0004253198082],"iteration":846,"passed_time":35.52884222,"remaining_time":6.417842809},
{"learn":[0.0004249374072],"iteration":847,"passed_time":35.58418625,"remaining_time":6.378297536},
{"learn":[0.0004245268181],"iteration":848,"passed_time":35.63938002,"remaining_time":6.33868832},
{"learn":[0.0004241552825],"iteration":849,"passed_time":35.69651516,"remaining_time":6.299385028},
{"learn":[0.000423776793],"iteration":850,"passed_time":35.75615204,"remaining_time":6.260477855},
{"learn":[0.0004229286065],"iteration":851,"passed_time":35.78484698,"remaining_time":6.216147128},
{"learn":[0.0004225511104],"iteration":852,"passed_time":35.80913993,"remaining_time":6.171094455},
{"learn":[0.0004222103705],"iteration":853,"passed_time":35.86628956,"remaining_time":6.131707582},
{"learn":[0.0004213908377],"iteration":854,"passed_time":35.88812255,"remaining_time":6.086289789},
{"learn":[0.0004209736052],"iteration":855,"passed_time":35.94990311,"remaining_time":6.047647253},
{"learn":[0.0004204951848],"iteration":856,"passed_time":35.97691604,"remaining_time":6.003149351},
{"learn":[0.0004199122389],"iteration":857,"passed_time":36.00236081,"remaining_time":5.958432675},
{"learn":[0.0004193817576],"iteration":858,"passed_time":36.0501572,"remaining_time":5.917429762},
{"learn":[0.0004188563675],"iteration":859,"passed_time":36.07458024,"remaining_time":5.872606085},
{"learn":[0.0004186100016],"iteration":860,"passed_time":36.13691375,"remaining_time":5.833950071},
{"learn":[0.0004181839526],"iteration":861,"passed_time":36.19970639,"remaining_time":5.795312624},
{"learn":[0.0004174343],"iteration":862,"passed_time":36.23157686,"remaining_time":5.751710348},
{"learn":[0.0004169177264],"iteration":863,"passed_time":36.27650022,"remaining_time":5.71018985},
{"learn":[0.0004163904736],"iteration":864,"passed_time":36.30563458,"remaining_time":5.666197305},
{"learn":[0.0004159007221],"iteration":865,"passed_time":36.36501521,"remaining_time":5.626919212},
{"learn":[0.0004154964661],"iteration":866,"passed_time":36.42509813,"remaining_time":5.587702482},
{"learn":[0.000415029563],"iteration":867,"passed_time":36.48156228,"remaining_time":5.547887351},
{"learn":[0.0004144557441],"iteration":868,"passed_time":36.50698626,"remaining_time":5.503354661},
{"learn":[0.0004139412194],"iteration":869,"passed_time":36.52976783,"remaining_time":5.458471055},
{"learn":[0.0004136127109],"iteration":870,"passed_time":36.5893376,"remaining_time":5.419086741},
{"learn":[0.0004132411753],"iteration":871,"passed_time":36.65056959,"remaining_time":5.379900123},
{"learn":[0.0004128338769],"iteration":872,"passed_time":36.71222939,"remaining_time":5.340725238},
{"learn":[0.0004126669839],"iteration":873,"passed_time":36.77440224,"remaining_time":5.301572863},
{"learn":[0.0004122720721],"iteration":874,"passed_time":36.8336721,"remaining_time":5.261953156},
{"learn":[0.0004117464026],"iteration":875,"passed_time":36.89493687,"remaining_time":5.222570972},
{"learn":[0.0004111751914],"iteration":876,"passed_time":36.9448121,"remaining_time":5.181541491},
{"learn":[0.0004109874989],"iteration":877,"passed_time":36.97438891,"remaining_time":5.137671352},
{"learn":[0.0004100786832],"iteration":878,"passed_time":36.99774772,"remaining_time":5.092977786},
{"learn":[0.0004092720648],"iteration":879,"passed_time":37.02787921,"remaining_time":5.049256255},
{"learn":[0.0004088498652],"iteration":880,"passed_time":37.09209163,"remaining_time":5.010169017},
{"learn":[0.0004084979184],"iteration":881,"passed_time":37.12445765,"remaining_time":4.966764175},
{"learn":[0.0004079651088],"iteration":882,"passed_time":37.15080731,"remaining_time":4.922587152},
{"learn":[0.0004076445786],"iteration":883,"passed_time":37.21242254,"remaining_time":4.883078071},
{"learn":[0.0004073137728],"iteration":884,"passed_time":37.27278679,"remaining_time":4.843356476},
{"learn":[0.0004066174229],"iteration":885,"passed_time":37.3087469,"remaining_time":4.800448247},
{"learn":[0.0004060332974],"iteration":886,"passed_time":37.33988433,"remaining_time":4.756941296},
{"learn":[0.0004058058063],"iteration":887,"passed_time":37.37094683,"remaining_time":4.713452754},
{"learn":[0.0004049147169],"iteration":888,"passed_time":37.39789596,"remaining_time":4.669478573},
{"learn":[0.0004046474894],"iteration":889,"passed_time":37.45965683,"remaining_time":4.629845226},
{"learn":[0.0004042630705],"iteration":890,"passed_time":37.52106093,"remaining_time":4.590118565},
{"learn":[0.0004038398775],"iteration":891,"passed_time":37.57861083,"remaining_time":4.549876648},
{"learn":[0.0004033001761],"iteration":892,"passed_time":37.63860129,"remaining_time":4.509888396},
{"learn":[0.0004024221251],"iteration":893,"passed_time":37.6624778,"remaining_time":4.46557343},
{"learn":[0.0004016254408],"iteration":894,"passed_time":37.69084019,"remaining_time":4.421830413},
{"learn":[0.0004011595622],"iteration":895,"passed_time":37.7501355,"remaining_time":4.381712156},
{"learn":[0.0004008307432],"iteration":896,"passed_time":37.81162883,"remaining_time":4.341803534},
{"learn":[0.0004005420022],"iteration":897,"passed_time":37.87085789,"remaining_time":4.301589649},
{"learn":[0.0004000721189],"iteration":898,"passed_time":37.92974149,"remaining_time":4.261294651},
{"learn":[0.0003996946538],"iteration":899,"passed_time":37.99061416,"remaining_time":4.221179351},
{"learn":[0.0003992059889],"iteration":900,"passed_time":38.01421742,"remaining_time":4.176922891},
{"learn":[0.0003987897808],"iteration":901,"passed_time":38.04192868,"remaining_time":4.133158548},
{"learn":[0.0003982374445],"iteration":902,"passed_time":38.06524395,"remaining_time":4.088957545},
{"learn":[0.000398064591],"iteration":903,"passed_time":38.12540039,"remaining_time":4.048715085},
{"learn":[0.000397154068],"iteration":904,"passed_time":38.15547767,"remaining_time":4.005271136},
{"learn":[0.0003966134042],"iteration":905,"passed_time":38.18071311,"remaining_time":3.96135434},
{"learn":[0.000396368218],"iteration":906,"passed_time":38.20557158,"remaining_time":3.917440085},
{"learn":[0.0003961082858],"iteration":907,"passed_time":38.22941733,"remaining_time":3.873465192},
{"learn":[0.0003952301728],"iteration":908,"passed_time":38.25489682,"remaining_time":3.829698141},
{"learn":[0.0003948586682],"iteration":909,"passed_time":38.31730118,"remaining_time":3.789623194},
{"learn":[0.0003944483896],"iteration":910,"passed_time":38.36388558,"remaining_time":3.747953696},
{"learn":[0.0003940967222],"iteration":911,"passed_time":38.42580274,"remaining_time":3.707752896},
{"learn":[0.0003936766336],"iteration":912,"passed_time":38.48569081,"remaining_time":3.667311172},
{"learn":[0.0003934580833],"iteration":913,"passed_time":38.54385943,"remaining_time":3.62666511},
{"learn":[0.000393123397],"iteration":914,"passed_time":38.60480522,"remaining_time":3.586238736},
{"learn":[0.0003929545172],"iteration":915,"passed_time":38.6634282,"remaining_time":3.545554551},
{"learn":[0.0003920867418],"iteration":916,"passed_time":38.6948422,"remaining_time":3.502368487},
{"learn":[0.0003912244613],"iteration":917,"passed_time":38.71985672,"remaining_time":3.458636439},
{"learn":[0.0003909373656],"iteration":918,"passed_time":38.77983416,"remaining_time":3.418026732},
{"learn":[0.000390091973],"iteration":919,"passed_time":38.80601372,"remaining_time":3.374435976},
{"learn":[0.0003898485874],"iteration":920,"passed_time":38.83115285,"remaining_time":3.330793784},
{"learn":[0.0003893847267],"iteration":921,"passed_time":38.86839155,"remaining_time":3.288215337},
{"learn":[0.0003890081309],"iteration":922,"passed_time":38.93259136,"remaining_time":3.247897654},
{"learn":[0.0003885352984],"iteration":923,"passed_time":38.9795654,"remaining_time":3.20611144},
{"learn":[0.0003881042513],"iteration":924,"passed_time":39.00412311,"remaining_time":3.162496468},
{"learn":[0.0003877088738],"iteration":925,"passed_time":39.02726787,"remaining_time":3.118809743},
{"learn":[0.0003873810483],"iteration":926,"passed_time":39.05577599,"remaining_time":3.075589695},
{"learn":[0.0003870244448],"iteration":927,"passed_time":39.11554549,"remaining_time":3.034826805},
{"learn":[0.0003867840394],"iteration":928,"passed_time":39.17493952,"remaining_time":2.993994301},
{"learn":[0.000386333093],"iteration":929,"passed_time":39.19975,"remaining_time":2.950518817},
{"learn":[0.000385999307],"iteration":930,"passed_time":39.25883256,"remaining_time":2.909623466},
{"learn":[0.000385626778],"iteration":931,"passed_time":39.31996205,"remaining_time":2.868838433},
{"learn":[0.0003848949758],"iteration":932,"passed_time":39.35115162,"remaining_time":2.825859763},
{"learn":[0.0003840227922],"iteration":933,"passed_time":39.37898499,"remaining_time":2.782669175},
{"learn":[0.0003836443648],"iteration":934,"passed_time":39.40842396,"remaining_time":2.739623056},
{"learn":[0.0003833891824],"iteration":935,"passed_time":39.46953862,"remaining_time":2.698771871},
{"learn":[0.0003829560553],"iteration":936,"passed_time":39.52613849,"remaining_time":2.657573879},
{"learn":[0.000382349547],"iteration":937,"passed_time":39.58590949,"remaining_time":2.616552653},
{"learn":[0.0003821350634],"iteration":938,"passed_time":39.60915664,"remaining_time":2.573118802},
{"learn":[0.0003816321492],"iteration":939,"passed_time":39.67005155,"remaining_time":2.53213095},
{"learn":[0.0003813264892],"iteration":940,"passed_time":39.69367301,"remaining_time":2.48876377},
{"learn":[0.0003809748217],"iteration":941,"passed_time":39.7541228,"remaining_time":2.447706075},
{"learn":[0.0003801699107],"iteration":942,"passed_time":39.77727942,"remaining_time":2.404353051},
{"learn":[0.0003794709221],"iteration":943,"passed_time":39.80604939,"remaining_time":2.361375811},
{"learn":[0.0003790944194],"iteration":944,"passed_time":39.86590903,"remaining_time":2.320238092},
{"learn":[0.000378670264],"iteration":945,"passed_time":39.90850793,"remaining_time":2.278075505},
{"learn":[0.0003785510547],"iteration":946,"passed_time":39.9672126,"remaining_time":2.236813377},
{"learn":[0.0003779632971],"iteration":947,"passed_time":40.01264059,"remaining_time":2.194786192},
{"learn":[0.0003776198253],"iteration":948,"passed_time":40.07239545,"remaining_time":2.153521779},
{"learn":[0.0003773834867],"iteration":949,"passed_time":40.13415027,"remaining_time":2.112323698},
{"learn":[0.0003770377797],"iteration":950,"passed_time":40.15874218,"remaining_time":2.069167578},
{"learn":[0.0003766135933],"iteration":951,"passed_time":40.20277139,"remaining_time":2.02703049},
{"learn":[0.0003762708666],"iteration":952,"passed_time":40.26052114,"remaining_time":1.9855661},
{"learn":[0.0003759142322],"iteration":953,"passed_time":40.28443262,"remaining_time":1.942435955},
{"learn":[0.000375621176],"iteration":954,"passed_time":40.34113787,"remaining_time":1.900891313},
{"learn":[0.0003754513028],"iteration":955,"passed_time":40.3659587,"remaining_time":1.857847472},
{"learn":[0.0003750114391],"iteration":956,"passed_time":40.38913782,"remaining_time":1.814767948},
{"learn":[0.0003746667256],"iteration":957,"passed_time":40.44994932,"remaining_time":1.773379824},
{"learn":[0.0003744720171],"iteration":958,"passed_time":40.47284459,"remaining_time":1.730330165},
{"learn":[0.0003737021238],"iteration":959,"passed_time":40.49986181,"remaining_time":1.687494242},
{"learn":[0.0003729630262],"iteration":960,"passed_time":40.52453427,"remaining_time":1.644596084},
{"learn":[0.0003722396369],"iteration":961,"passed_time":40.55565308,"remaining_time":1.601990454},
{"learn":[0.0003718353187],"iteration":962,"passed_time":40.60189912,"remaining_time":1.559989893},
{"learn":[0.0003715184207],"iteration":963,"passed_time":40.66326119,"remaining_time":1.518545024},
{"learn":[0.0003708222881],"iteration":964,"passed_time":40.6868776,"remaining_time":1.475689861},
{"learn":[0.0003701487556],"iteration":965,"passed_time":40.71209396,"remaining_time":1.432930843},
{"learn":[0.0003695974437],"iteration":966,"passed_time":40.75688364,"remaining_time":1.39087607},
{"learn":[0.0003691487635],"iteration":967,"passed_time":40.78594903,"remaining_time":1.348295836},
{"learn":[0.000368775924],"iteration":968,"passed_time":40.81225367,"remaining_time":1.305655174},
{"learn":[0.0003684107525],"iteration":969,"passed_time":40.83552133,"remaining_time":1.262954268},
{"learn":[0.0003680809401],"iteration":970,"passed_time":40.89795168,"remaining_time":1.221463026},
{"learn":[0.0003677551324],"iteration":971,"passed_time":40.93362367,"remaining_time":1.179157884},
{"learn":[0.0003669884987],"iteration":972,"passed_time":40.96598183,"remaining_time":1.136774419},
{"learn":[0.000366445103],"iteration":973,"passed_time":40.99534963,"remaining_time":1.094331715},
{"learn":[0.0003658749163],"iteration":974,"passed_time":41.03032839,"remaining_time":1.052059702},
{"learn":[0.0003653024013],"iteration":975,"passed_time":41.05359375,"remaining_time":1.009514601},
{"learn":[0.0003649924571],"iteration":976,"passed_time":41.11530394,"remaining_time":0.967914013},
{"learn":[0.0003646725789],"iteration":977,"passed_time":41.17296515,"remaining_time":0.9261812202},
{"learn":[0.0003644699541],"iteration":978,"passed_time":41.23268855,"remaining_time":0.884460122},
{"learn":[0.0003643189246],"iteration":979,"passed_time":41.25844468,"remaining_time":0.842009075},
{"learn":[0.0003639087081],"iteration":980,"passed_time":41.31837993,"remaining_time":0.8002540455},
{"learn":[0.0003635133927],"iteration":981,"passed_time":41.3787958,"remaining_time":0.7584707988},
{"learn":[0.0003631697036],"iteration":982,"passed_time":41.40375527,"remaining_time":0.7160364594},
{"learn":[0.0003626402467],"iteration":983,"passed_time":41.4323186,"remaining_time":0.6736962375},
{"learn":[0.0003622697356],"iteration":984,"passed_time":41.49130726,"remaining_time":0.6318473187},
{"learn":[0.0003621008868],"iteration":985,"passed_time":41.54794154,"remaining_time":0.5899302044},
{"learn":[0.0003614525621],"iteration":986,"passed_time":41.57226586,"remaining_time":0.5475577064},
{"learn":[0.0003607456262],"iteration":987,"passed_time":41.60037348,"remaining_time":0.5052676941},
{"learn":[0.0003604108468],"iteration":988,"passed_time":41.62816587,"remaining_time":0.463002856},
{"learn":[0.0003599846736],"iteration":989,"passed_time":41.68614841,"remaining_time":0.4210722062},
{"learn":[0.0003596887303],"iteration":990,"passed_time":41.74534871,"remaining_time":0.3791202204},
{"learn":[0.0003591434099],"iteration":991,"passed_time":41.77523582,"remaining_time":0.336897063},
{"learn":[0.0003588821429],"iteration":992,"passed_time":41.80446135,"remaining_time":0.2946940881},
{"learn":[0.0003585404406],"iteration":993,"passed_time":41.86657018,"remaining_time":0.2527157153},
{"learn":[0.0003579255193],"iteration":994,"passed_time":41.8945867,"remaining_time":0.2105255613},
{"learn":[0.0003575252369],"iteration":995,"passed_time":41.91860542,"remaining_time":0.1683478129},
{"learn":[0.0003573305284],"iteration":996,"passed_time":41.97953176,"remaining_time":0.1263175479},
{"learn":[0.0003570397695],"iteration":997,"passed_time":42.03863361,"remaining_time":0.08424575874},
{"learn":[0.0003569116816],"iteration":998,"passed_time":42.09553294,"remaining_time":0.04213767061},
{"learn":[0.0003563812003],"iteration":999,"passed_time":42.12445182,"remaining_time":0}
]}